{
  "config": "{\"version\":\"5.66\",\"themeCollection\":{\"baseTheme\":{\"name\":\"CY24SU10\",\"type\":2,\"version\":{\"visual\":\"1.8.95\",\"report\":\"2.0.95\",\"page\":\"1.3.95\"}}},\"activeSectionIndex\":0,\"defaultDrillFilterOtherVisuals\":true,\"linguisticSchemaSyncVersion\":2,\"settings\":{\"useNewFilterPaneExperience\":true,\"allowChangeFilterTypes\":true,\"useStylableVisualContainerHeader\":true,\"queryLimitOption\":6,\"exportDataMode\":1,\"useDefaultAggregateDisplayName\":true,\"useEnhancedTooltips\":true},\"objects\":{\"section\":[{\"properties\":{\"verticalAlignment\":{\"expr\":{\"Literal\":{\"Value\":\"'Top'\"}}}}}],\"outspacePane\":[{\"properties\":{\"expanded\":{\"expr\":{\"Literal\":{\"Value\":\"false\"}}}}}]}}",
  "layoutOptimization": 0,
  "publicCustomVisuals": [
    "htmlContent443BE3AD55E043BF878BED274D3A6855",
    "htmlContent443BE3AD55E043BF878BED274D3A6865"
  ],
  "resourcePackages": [
    {
      "resourcePackage": {
        "disabled": false,
        "items": [
          {
            "name": "CY24SU10",
            "path": "BaseThemes/CY24SU10.json",
            "type": 202
          }
        ],
        "name": "SharedResources",
        "type": 2
      }
    }
  ],
  "sections": [
    {
      "config": "{}",
      "displayName": "Visao Executiva",
      "displayOption": 1,
      "filters": "[]",
      "height": 720.0,
      "name": "sec_visao_executiva",
      "ordinal": 0,
      "visualContainers": [
        {
          "config": "{\"name\":\"v6708823867054db7b8b\",\"layouts\":[{\"id\":0,\"position\":{\"x\":24,\"y\":20,\"z\":100,\"width\":540,\"height\":78,\"tabOrder\":100}}],\"singleVisual\":{\"visualType\":\"htmlContent443BE3AD55E043BF878BED274D3A6865\",\"drillFilterOtherVisuals\":true,\"projections\":{\"content\":[{\"queryRef\":\"medidas.HTML Header Visao\"}]},\"prototypeQuery\":{\"Version\":2,\"From\":[{\"Name\":\"m\",\"Entity\":\"medidas\",\"Type\":0}],\"Select\":[{\"Measure\":{\"Expression\":{\"SourceRef\":{\"Source\":\"m\"}},\"Property\":\"HTML Header Visao\"},\"Name\":\"medidas.HTML Header Visao\",\"NativeReferenceName\":\"HTML Header Visao\"}]},\"hasDefaultSort\":true,\"objects\":{}}}",
          "filters": "[]",
          "height": 78.0,
          "width": 540.0,
          "x": 24.0,
          "y": 20.0,
          "z": 100.0
        },
        {
          "config": "{\"name\":\"v26780d72172f4454a74\",\"layouts\":[{\"id\":0,\"position\":{\"x\":584,\"y\":37,\"z\":150,\"width\":420,\"height\":36,\"tabOrder\":150}}],\"singleVisual\":{\"visualType\":\"pageNavigator\",\"drillFilterOtherVisuals\":true}}",
          "filters": "[]",
          "height": 36.0,
          "width": 420.0,
          "x": 584.0,
          "y": 37.0,
          "z": 150.0
        },
        {
          "config": "{\"name\":\"v1d169e41c8c34e7a803\",\"layouts\":[{\"id\":0,\"position\":{\"x\":1024,\"y\":20,\"z\":50,\"width\":232,\"height\":676,\"tabOrder\":50}}],\"singleVisual\":{\"visualType\":\"htmlContent443BE3AD55E043BF878BED274D3A6865\",\"drillFilterOtherVisuals\":true,\"projections\":{\"content\":[{\"queryRef\":\"medidas.HTML Filter Panel\"}]},\"prototypeQuery\":{\"Version\":2,\"From\":[{\"Name\":\"m\",\"Entity\":\"medidas\",\"Type\":0}],\"Select\":[{\"Measure\":{\"Expression\":{\"SourceRef\":{\"Source\":\"m\"}},\"Property\":\"HTML Filter Panel\"},\"Name\":\"medidas.HTML Filter Panel\",\"NativeReferenceName\":\"HTML Filter Panel\"}]},\"hasDefaultSort\":true,\"objects\":{}}}",
          "filters": "[]",
          "height": 676.0,
          "width": 232.0,
          "x": 1024.0,
          "y": 20.0,
          "z": 50.0
        },
        {
          "config": "{\"name\":\"vb2d96876d2d44c40a46\",\"layouts\":[{\"id\":0,\"position\":{\"x\":1042,\"y\":164,\"z\":10000,\"width\":196,\"height\":58,\"tabOrder\":10000}}],\"singleVisual\":{\"visualType\":\"slicer\",\"drillFilterOtherVisuals\":true,\"projections\":{\"Values\":[{\"queryRef\":\"dim_calendario.Ano\",\"active\":true}]},\"prototypeQuery\":{\"Version\":2,\"From\":[{\"Name\":\"d\",\"Entity\":\"dim_calendario\",\"Type\":0}],\"Select\":[{\"Column\":{\"Expression\":{\"SourceRef\":{\"Source\":\"d\"}},\"Property\":\"Ano\"},\"Name\":\"dim_calendario.Ano\",\"NativeReferenceName\":\"Ano\"}]},\"hasDefaultSort\":true,\"objects\":{\"title\":[{\"properties\":{\"text\":{\"expr\":{\"Literal\":{\"Value\":\"'Ano'\"}}}}}]}}}",
          "filters": "[]",
          "height": 58.0,
          "width": 196.0,
          "x": 1042.0,
          "y": 164.0,
          "z": 10000.0
        },
        {
          "config": "{\"name\":\"vfdb832407d9d4830aaa\",\"layouts\":[{\"id\":0,\"position\":{\"x\":1042,\"y\":234,\"z\":10001,\"width\":196,\"height\":58,\"tabOrder\":10001}}],\"singleVisual\":{\"visualType\":\"slicer\",\"drillFilterOtherVisuals\":true,\"projections\":{\"Values\":[{\"queryRef\":\"dim_calendario.Mes Nome\",\"active\":true}]},\"prototypeQuery\":{\"Version\":2,\"From\":[{\"Name\":\"d\",\"Entity\":\"dim_calendario\",\"Type\":0}],\"Select\":[{\"Column\":{\"Expression\":{\"SourceRef\":{\"Source\":\"d\"}},\"Property\":\"Mes Nome\"},\"Name\":\"dim_calendario.Mes Nome\",\"NativeReferenceName\":\"Mes Nome\"}]},\"hasDefaultSort\":true,\"objects\":{\"title\":[{\"properties\":{\"text\":{\"expr\":{\"Literal\":{\"Value\":\"'Mes'\"}}}}}]}}}",
          "filters": "[]",
          "height": 58.0,
          "width": 196.0,
          "x": 1042.0,
          "y": 234.0,
          "z": 10001.0
        },
        {
          "config": "{\"name\":\"v7cceae1e780e41dfad9\",\"layouts\":[{\"id\":0,\"position\":{\"x\":1042,\"y\":304,\"z\":10002,\"width\":196,\"height\":58,\"tabOrder\":10002}}],\"singleVisual\":{\"visualType\":\"slicer\",\"drillFilterOtherVisuals\":true,\"projections\":{\"Values\":[{\"queryRef\":\"dim_categoria.nome_categoria\",\"active\":true}]},\"prototypeQuery\":{\"Version\":2,\"From\":[{\"Name\":\"c\",\"Entity\":\"dim_categoria\",\"Type\":0}],\"Select\":[{\"Column\":{\"Expression\":{\"SourceRef\":{\"Source\":\"c\"}},\"Property\":\"nome_categoria\"},\"Name\":\"dim_categoria.nome_categoria\",\"NativeReferenceName\":\"nome_categoria\"}]},\"hasDefaultSort\":true,\"objects\":{\"title\":[{\"properties\":{\"text\":{\"expr\":{\"Literal\":{\"Value\":\"'Categoria'\"}}}}}]}}}",
          "filters": "[]",
          "height": 58.0,
          "width": 196.0,
          "x": 1042.0,
          "y": 304.0,
          "z": 10002.0
        },
        {
          "config": "{\"name\":\"v745bb020ffa14cdabbc\",\"layouts\":[{\"id\":0,\"position\":{\"x\":1042,\"y\":374,\"z\":10003,\"width\":196,\"height\":58,\"tabOrder\":10003}}],\"singleVisual\":{\"visualType\":\"slicer\",\"drillFilterOtherVisuals\":true,\"projections\":{\"Values\":[{\"queryRef\":\"dim_forma_pagamento.forma\",\"active\":true}]},\"prototypeQuery\":{\"Version\":2,\"From\":[{\"Name\":\"p\",\"Entity\":\"dim_forma_pagamento\",\"Type\":0}],\"Select\":[{\"Column\":{\"Expression\":{\"SourceRef\":{\"Source\":\"p\"}},\"Property\":\"forma\"},\"Name\":\"dim_forma_pagamento.forma\",\"NativeReferenceName\":\"forma\"}]},\"hasDefaultSort\":true,\"objects\":{\"title\":[{\"properties\":{\"text\":{\"expr\":{\"Literal\":{\"Value\":\"'Forma'\"}}}}}]}}}",
          "filters": "[]",
          "height": 58.0,
          "width": 196.0,
          "x": 1042.0,
          "y": 374.0,
          "z": 10003.0
        },
        {
          "config": "{\"name\":\"v2b4d38483c7647a9b32\",\"layouts\":[{\"id\":0,\"position\":{\"x\":1042,\"y\":444,\"z\":10004,\"width\":196,\"height\":58,\"tabOrder\":10004}}],\"singleVisual\":{\"visualType\":\"slicer\",\"drillFilterOtherVisuals\":true,\"projections\":{\"Values\":[{\"queryRef\":\"fat_lancamentos_financeiros.tipo\",\"active\":true}]},\"prototypeQuery\":{\"Version\":2,\"From\":[{\"Name\":\"f\",\"Entity\":\"fat_lancamentos_financeiros\",\"Type\":0}],\"Select\":[{\"Column\":{\"Expression\":{\"SourceRef\":{\"Source\":\"f\"}},\"Property\":\"tipo\"},\"Name\":\"fat_lancamentos_financeiros.tipo\",\"NativeReferenceName\":\"tipo\"}]},\"hasDefaultSort\":true,\"objects\":{\"title\":[{\"properties\":{\"text\":{\"expr\":{\"Literal\":{\"Value\":\"'Tipo'\"}}}}}]}}}",
          "filters": "[]",
          "height": 58.0,
          "width": 196.0,
          "x": 1042.0,
          "y": 444.0,
          "z": 10004.0
        },
        {
          "config": "{\"name\":\"vef9f42e5914146e8a9e\",\"layouts\":[{\"id\":0,\"position\":{\"x\":24,\"y\":116,\"z\":1000,\"width\":184,\"height\":118,\"tabOrder\":1000}}],\"singleVisual\":{\"visualType\":\"htmlContent443BE3AD55E043BF878BED274D3A6865\",\"drillFilterOtherVisuals\":true,\"projections\":{\"content\":[{\"queryRef\":\"medidas.HTML KPI Receita\"}]},\"prototypeQuery\":{\"Version\":2,\"From\":[{\"Name\":\"m\",\"Entity\":\"medidas\",\"Type\":0}],\"Select\":[{\"Measure\":{\"Expression\":{\"SourceRef\":{\"Source\":\"m\"}},\"Property\":\"HTML KPI Receita\"},\"Name\":\"medidas.HTML KPI Receita\",\"NativeReferenceName\":\"HTML KPI Receita\"}]},\"hasDefaultSort\":true,\"objects\":{}}}",
          "filters": "[]",
          "height": 118.0,
          "width": 184.0,
          "x": 24.0,
          "y": 116.0,
          "z": 1000.0
        },
        {
          "config": "{\"name\":\"v02dbdbb47bdf4028b68\",\"layouts\":[{\"id\":0,\"position\":{\"x\":222,\"y\":116,\"z\":1001,\"width\":184,\"height\":118,\"tabOrder\":1001}}],\"singleVisual\":{\"visualType\":\"htmlContent443BE3AD55E043BF878BED274D3A6865\",\"drillFilterOtherVisuals\":true,\"projections\":{\"content\":[{\"queryRef\":\"medidas.HTML KPI Despesa\"}]},\"prototypeQuery\":{\"Version\":2,\"From\":[{\"Name\":\"m\",\"Entity\":\"medidas\",\"Type\":0}],\"Select\":[{\"Measure\":{\"Expression\":{\"SourceRef\":{\"Source\":\"m\"}},\"Property\":\"HTML KPI Despesa\"},\"Name\":\"medidas.HTML KPI Despesa\",\"NativeReferenceName\":\"HTML KPI Despesa\"}]},\"hasDefaultSort\":true,\"objects\":{}}}",
          "filters": "[]",
          "height": 118.0,
          "width": 184.0,
          "x": 222.0,
          "y": 116.0,
          "z": 1001.0
        },
        {
          "config": "{\"name\":\"v475b2a9c87944906b71\",\"layouts\":[{\"id\":0,\"position\":{\"x\":420,\"y\":116,\"z\":1002,\"width\":184,\"height\":118,\"tabOrder\":1002}}],\"singleVisual\":{\"visualType\":\"htmlContent443BE3AD55E043BF878BED274D3A6865\",\"drillFilterOtherVisuals\":true,\"projections\":{\"content\":[{\"queryRef\":\"medidas.HTML KPI Resultado\"}]},\"prototypeQuery\":{\"Version\":2,\"From\":[{\"Name\":\"m\",\"Entity\":\"medidas\",\"Type\":0}],\"Select\":[{\"Measure\":{\"Expression\":{\"SourceRef\":{\"Source\":\"m\"}},\"Property\":\"HTML KPI Resultado\"},\"Name\":\"medidas.HTML KPI Resultado\",\"NativeReferenceName\":\"HTML KPI Resultado\"}]},\"hasDefaultSort\":true,\"objects\":{}}}",
          "filters": "[]",
          "height": 118.0,
          "width": 184.0,
          "x": 420.0,
          "y": 116.0,
          "z": 1002.0
        },
        {
          "config": "{\"name\":\"vdd9a3c51694643b8be6\",\"layouts\":[{\"id\":0,\"position\":{\"x\":618,\"y\":116,\"z\":1003,\"width\":184,\"height\":118,\"tabOrder\":1003}}],\"singleVisual\":{\"visualType\":\"htmlContent443BE3AD55E043BF878BED274D3A6865\",\"drillFilterOtherVisuals\":true,\"projections\":{\"content\":[{\"queryRef\":\"medidas.HTML KPI Margem\"}]},\"prototypeQuery\":{\"Version\":2,\"From\":[{\"Name\":\"m\",\"Entity\":\"medidas\",\"Type\":0}],\"Select\":[{\"Measure\":{\"Expression\":{\"SourceRef\":{\"Source\":\"m\"}},\"Property\":\"HTML KPI Margem\"},\"Name\":\"medidas.HTML KPI Margem\",\"NativeReferenceName\":\"HTML KPI Margem\"}]},\"hasDefaultSort\":true,\"objects\":{}}}",
          "filters": "[]",
          "height": 118.0,
          "width": 184.0,
          "x": 618.0,
          "y": 116.0,
          "z": 1003.0
        },
        {
          "config": "{\"name\":\"va901225c5536427bb86\",\"layouts\":[{\"id\":0,\"position\":{\"x\":816,\"y\":116,\"z\":1004,\"width\":184,\"height\":118,\"tabOrder\":1004}}],\"singleVisual\":{\"visualType\":\"htmlContent443BE3AD55E043BF878BED274D3A6865\",\"drillFilterOtherVisuals\":true,\"projections\":{\"content\":[{\"queryRef\":\"medidas.HTML KPI Lancamentos\"}]},\"prototypeQuery\":{\"Version\":2,\"From\":[{\"Name\":\"m\",\"Entity\":\"medidas\",\"Type\":0}],\"Select\":[{\"Measure\":{\"Expression\":{\"SourceRef\":{\"Source\":\"m\"}},\"Property\":\"HTML KPI Lancamentos\"},\"Name\":\"medidas.HTML KPI Lancamentos\",\"NativeReferenceName\":\"HTML KPI Lancamentos\"}]},\"hasDefaultSort\":true,\"objects\":{}}}",
          "filters": "[]",
          "height": 118.0,
          "width": 184.0,
          "x": 816.0,
          "y": 116.0,
          "z": 1004.0
        },
        {
          "config": "{\"name\":\"v7dc1e27bc70e4579a7e\",\"layouts\":[{\"id\":0,\"position\":{\"x\":24,\"y\":256,\"z\":2000,\"width\":640,\"height\":220,\"tabOrder\":2000}}],\"singleVisual\":{\"visualType\":\"lineChart\",\"drillFilterOtherVisuals\":true,\"projections\":{\"Category\":[{\"queryRef\":\"dim_calendario.Ano Mes\",\"active\":true}],\"Y\":[{\"queryRef\":\"medidas.Receita Total\"},{\"queryRef\":\"medidas.Despesa Total\"},{\"queryRef\":\"medidas.Resultado\"}],\"Tooltips\":[{\"queryRef\":\"medidas.Receita Total\"},{\"queryRef\":\"medidas.Despesa Total\"},{\"queryRef\":\"medidas.Resultado\"},{\"queryRef\":\"medidas.Margem de Resultado %\"}]},\"prototypeQuery\":{\"Version\":2,\"From\":[{\"Name\":\"d\",\"Entity\":\"dim_calendario\",\"Type\":0},{\"Name\":\"m\",\"Entity\":\"medidas\",\"Type\":0}],\"Select\":[{\"Column\":{\"Expression\":{\"SourceRef\":{\"Source\":\"d\"}},\"Property\":\"Ano Mes\"},\"Name\":\"dim_calendario.Ano Mes\",\"NativeReferenceName\":\"Ano Mes\"},{\"Measure\":{\"Expression\":{\"SourceRef\":{\"Source\":\"m\"}},\"Property\":\"Receita Total\"},\"Name\":\"medidas.Receita Total\",\"NativeReferenceName\":\"Receita Total\"},{\"Measure\":{\"Expression\":{\"SourceRef\":{\"Source\":\"m\"}},\"Property\":\"Despesa Total\"},\"Name\":\"medidas.Despesa Total\",\"NativeReferenceName\":\"Despesa Total\"},{\"Measure\":{\"Expression\":{\"SourceRef\":{\"Source\":\"m\"}},\"Property\":\"Resultado\"},\"Name\":\"medidas.Resultado\",\"NativeReferenceName\":\"Resultado\"},{\"Measure\":{\"Expression\":{\"SourceRef\":{\"Source\":\"m\"}},\"Property\":\"Margem de Resultado %\"},\"Name\":\"medidas.Margem de Resultado %\",\"NativeReferenceName\":\"Margem de Resultado %\"}],\"OrderBy\":[{\"Direction\":1,\"Expression\":{\"Column\":{\"Expression\":{\"SourceRef\":{\"Source\":\"d\"}},\"Property\":\"Ano Mes\"}}}]},\"hasDefaultSort\":true,\"objects\":{\"title\":[{\"properties\":{\"text\":{\"expr\":{\"Literal\":{\"Value\":\"'Fluxo financeiro mensal'\"}}}}}]}}}",
          "filters": "[]",
          "height": 220.0,
          "width": 640.0,
          "x": 24.0,
          "y": 256.0,
          "z": 2000.0
        },
        {
          "config": "{\"name\":\"v8b8a580d77164487934\",\"layouts\":[{\"id\":0,\"position\":{\"x\":684,\"y\":256,\"z\":2001,\"width\":320,\"height\":220,\"tabOrder\":2001}}],\"singleVisual\":{\"visualType\":\"htmlContent443BE3AD55E043BF878BED274D3A6865\",\"drillFilterOtherVisuals\":true,\"projections\":{\"content\":[{\"queryRef\":\"medidas.HTML Insights Visao\"}]},\"prototypeQuery\":{\"Version\":2,\"From\":[{\"Name\":\"m\",\"Entity\":\"medidas\",\"Type\":0}],\"Select\":[{\"Measure\":{\"Expression\":{\"SourceRef\":{\"Source\":\"m\"}},\"Property\":\"HTML Insights Visao\"},\"Name\":\"medidas.HTML Insights Visao\",\"NativeReferenceName\":\"HTML Insights Visao\"}]},\"hasDefaultSort\":true,\"objects\":{}}}",
          "filters": "[]",
          "height": 220.0,
          "width": 320.0,
          "x": 684.0,
          "y": 256.0,
          "z": 2001.0
        },
        {
          "config": "{\"name\":\"vc736e146b26542b2a21\",\"layouts\":[{\"id\":0,\"position\":{\"x\":24,\"y\":500,\"z\":3000,\"width\":300,\"height\":196,\"tabOrder\":3000}}],\"singleVisual\":{\"visualType\":\"clusteredColumnChart\",\"drillFilterOtherVisuals\":true,\"projections\":{\"Category\":[{\"queryRef\":\"dim_calendario.Ano Mes\",\"active\":true}],\"Y\":[{\"queryRef\":\"medidas.Resultado\"}],\"Tooltips\":[{\"queryRef\":\"medidas.Receita Total\"},{\"queryRef\":\"medidas.Despesa Total\"},{\"queryRef\":\"medidas.Resultado\"},{\"queryRef\":\"medidas.Margem de Resultado %\"}]},\"prototypeQuery\":{\"Version\":2,\"From\":[{\"Name\":\"d\",\"Entity\":\"dim_calendario\",\"Type\":0},{\"Name\":\"m\",\"Entity\":\"medidas\",\"Type\":0}],\"Select\":[{\"Column\":{\"Expression\":{\"SourceRef\":{\"Source\":\"d\"}},\"Property\":\"Ano Mes\"},\"Name\":\"dim_calendario.Ano Mes\",\"NativeReferenceName\":\"Ano Mes\"},{\"Measure\":{\"Expression\":{\"SourceRef\":{\"Source\":\"m\"}},\"Property\":\"Resultado\"},\"Name\":\"medidas.Resultado\",\"NativeReferenceName\":\"Resultado\"},{\"Measure\":{\"Expression\":{\"SourceRef\":{\"Source\":\"m\"}},\"Property\":\"Receita Total\"},\"Name\":\"medidas.Receita Total\",\"NativeReferenceName\":\"Receita Total\"},{\"Measure\":{\"Expression\":{\"SourceRef\":{\"Source\":\"m\"}},\"Property\":\"Despesa Total\"},\"Name\":\"medidas.Despesa Total\",\"NativeReferenceName\":\"Despesa Total\"},{\"Measure\":{\"Expression\":{\"SourceRef\":{\"Source\":\"m\"}},\"Property\":\"Margem de Resultado %\"},\"Name\":\"medidas.Margem de Resultado %\",\"NativeReferenceName\":\"Margem de Resultado %\"}],\"OrderBy\":[{\"Direction\":1,\"Expression\":{\"Column\":{\"Expression\":{\"SourceRef\":{\"Source\":\"d\"}},\"Property\":\"Ano Mes\"}}}]},\"hasDefaultSort\":true,\"objects\":{\"title\":[{\"properties\":{\"text\":{\"expr\":{\"Literal\":{\"Value\":\"'Resultado por mes'\"}}}}}]}}}",
          "filters": "[]",
          "height": 196.0,
          "width": 300.0,
          "x": 24.0,
          "y": 500.0,
          "z": 3000.0
        },
        {
          "config": "{\"name\":\"v49af0a3c0a7c4e8cb50\",\"layouts\":[{\"id\":0,\"position\":{\"x\":344,\"y\":500,\"z\":3001,\"width\":300,\"height\":196,\"tabOrder\":3001}}],\"singleVisual\":{\"visualType\":\"clusteredBarChart\",\"drillFilterOtherVisuals\":true,\"projections\":{\"Category\":[{\"queryRef\":\"dim_categoria.nome_categoria\",\"active\":true}],\"Y\":[{\"queryRef\":\"medidas.Receita Total\"}],\"Tooltips\":[{\"queryRef\":\"medidas.Receita Total\"},{\"queryRef\":\"medidas.Despesa Total\"},{\"queryRef\":\"medidas.Resultado\"},{\"queryRef\":\"medidas.Margem de Resultado %\"}]},\"prototypeQuery\":{\"Version\":2,\"From\":[{\"Name\":\"c\",\"Entity\":\"dim_categoria\",\"Type\":0},{\"Name\":\"m\",\"Entity\":\"medidas\",\"Type\":0}],\"Select\":[{\"Column\":{\"Expression\":{\"SourceRef\":{\"Source\":\"c\"}},\"Property\":\"nome_categoria\"},\"Name\":\"dim_categoria.nome_categoria\",\"NativeReferenceName\":\"nome_categoria\"},{\"Measure\":{\"Expression\":{\"SourceRef\":{\"Source\":\"m\"}},\"Property\":\"Receita Total\"},\"Name\":\"medidas.Receita Total\",\"NativeReferenceName\":\"Receita Total\"},{\"Measure\":{\"Expression\":{\"SourceRef\":{\"Source\":\"m\"}},\"Property\":\"Despesa Total\"},\"Name\":\"medidas.Despesa Total\",\"NativeReferenceName\":\"Despesa Total\"},{\"Measure\":{\"Expression\":{\"SourceRef\":{\"Source\":\"m\"}},\"Property\":\"Resultado\"},\"Name\":\"medidas.Resultado\",\"NativeReferenceName\":\"Resultado\"},{\"Measure\":{\"Expression\":{\"SourceRef\":{\"Source\":\"m\"}},\"Property\":\"Margem de Resultado %\"},\"Name\":\"medidas.Margem de Resultado %\",\"NativeReferenceName\":\"Margem de Resultado %\"}],\"OrderBy\":[{\"Direction\":2,\"Expression\":{\"Measure\":{\"Expression\":{\"SourceRef\":{\"Source\":\"m\"}},\"Property\":\"Receita Total\"}}}]},\"hasDefaultSort\":true,\"objects\":{\"title\":[{\"properties\":{\"text\":{\"expr\":{\"Literal\":{\"Value\":\"'Top receitas'\"}}}}}]}}}",
          "filters": "[]",
          "height": 196.0,
          "width": 300.0,
          "x": 344.0,
          "y": 500.0,
          "z": 3001.0
        },
        {
          "config": "{\"name\":\"v8781bc17f4fb45ff8a2\",\"layouts\":[{\"id\":0,\"position\":{\"x\":664,\"y\":500,\"z\":3002,\"width\":340,\"height\":196,\"tabOrder\":3002}}],\"singleVisual\":{\"visualType\":\"donutChart\",\"drillFilterOtherVisuals\":true,\"projections\":{\"Category\":[{\"queryRef\":\"dim_forma_pagamento.forma\",\"active\":true}],\"Y\":[{\"queryRef\":\"medidas.Despesa Total\"}],\"Tooltips\":[{\"queryRef\":\"medidas.Receita Total\"},{\"queryRef\":\"medidas.Despesa Total\"},{\"queryRef\":\"medidas.Resultado\"},{\"queryRef\":\"medidas.Margem de Resultado %\"}]},\"prototypeQuery\":{\"Version\":2,\"From\":[{\"Name\":\"p\",\"Entity\":\"dim_forma_pagamento\",\"Type\":0},{\"Name\":\"m\",\"Entity\":\"medidas\",\"Type\":0}],\"Select\":[{\"Column\":{\"Expression\":{\"SourceRef\":{\"Source\":\"p\"}},\"Property\":\"forma\"},\"Name\":\"dim_forma_pagamento.forma\",\"NativeReferenceName\":\"forma\"},{\"Measure\":{\"Expression\":{\"SourceRef\":{\"Source\":\"m\"}},\"Property\":\"Despesa Total\"},\"Name\":\"medidas.Despesa Total\",\"NativeReferenceName\":\"Despesa Total\"},{\"Measure\":{\"Expression\":{\"SourceRef\":{\"Source\":\"m\"}},\"Property\":\"Receita Total\"},\"Name\":\"medidas.Receita Total\",\"NativeReferenceName\":\"Receita Total\"},{\"Measure\":{\"Expression\":{\"SourceRef\":{\"Source\":\"m\"}},\"Property\":\"Resultado\"},\"Name\":\"medidas.Resultado\",\"NativeReferenceName\":\"Resultado\"},{\"Measure\":{\"Expression\":{\"SourceRef\":{\"Source\":\"m\"}},\"Property\":\"Margem de Resultado %\"},\"Name\":\"medidas.Margem de Resultado %\",\"NativeReferenceName\":\"Margem de Resultado %\"}],\"OrderBy\":[{\"Direction\":2,\"Expression\":{\"Measure\":{\"Expression\":{\"SourceRef\":{\"Source\":\"m\"}},\"Property\":\"Despesa Total\"}}}]},\"hasDefaultSort\":true,\"objects\":{\"title\":[{\"properties\":{\"text\":{\"expr\":{\"Literal\":{\"Value\":\"'Despesas por forma'\"}}}}}]}}}",
          "filters": "[]",
          "height": 196.0,
          "width": 340.0,
          "x": 664.0,
          "y": 500.0,
          "z": 3002.0
        }
      ],
      "width": 1280.0
    },
    {
      "config": "{}",
      "displayName": "Receitas",
      "displayOption": 1,
      "filters": "[]",
      "height": 720.0,
      "name": "sec_receitas",
      "ordinal": 1,
      "visualContainers": [
        {
          "config": "{\"name\":\"vb07edff1a2b9405e9d3\",\"layouts\":[{\"id\":0,\"position\":{\"x\":24,\"y\":20,\"z\":100,\"width\":540,\"height\":78,\"tabOrder\":100}}],\"singleVisual\":{\"visualType\":\"htmlContent443BE3AD55E043BF878BED274D3A6865\",\"drillFilterOtherVisuals\":true,\"projections\":{\"content\":[{\"queryRef\":\"medidas.HTML Header Receitas\"}]},\"prototypeQuery\":{\"Version\":2,\"From\":[{\"Name\":\"m\",\"Entity\":\"medidas\",\"Type\":0}],\"Select\":[{\"Measure\":{\"Expression\":{\"SourceRef\":{\"Source\":\"m\"}},\"Property\":\"HTML Header Receitas\"},\"Name\":\"medidas.HTML Header Receitas\",\"NativeReferenceName\":\"HTML Header Receitas\"}]},\"hasDefaultSort\":true,\"objects\":{}}}",
          "filters": "[]",
          "height": 78.0,
          "width": 540.0,
          "x": 24.0,
          "y": 20.0,
          "z": 100.0
        },
        {
          "config": "{\"name\":\"v990d1c2299b8441f9de\",\"layouts\":[{\"id\":0,\"position\":{\"x\":584,\"y\":37,\"z\":150,\"width\":420,\"height\":36,\"tabOrder\":150}}],\"singleVisual\":{\"visualType\":\"pageNavigator\",\"drillFilterOtherVisuals\":true}}",
          "filters": "[]",
          "height": 36.0,
          "width": 420.0,
          "x": 584.0,
          "y": 37.0,
          "z": 150.0
        },
        {
          "config": "{\"name\":\"v2645b69b3eda40e1828\",\"layouts\":[{\"id\":0,\"position\":{\"x\":1024,\"y\":20,\"z\":50,\"width\":232,\"height\":676,\"tabOrder\":50}}],\"singleVisual\":{\"visualType\":\"htmlContent443BE3AD55E043BF878BED274D3A6865\",\"drillFilterOtherVisuals\":true,\"projections\":{\"content\":[{\"queryRef\":\"medidas.HTML Filter Panel\"}]},\"prototypeQuery\":{\"Version\":2,\"From\":[{\"Name\":\"m\",\"Entity\":\"medidas\",\"Type\":0}],\"Select\":[{\"Measure\":{\"Expression\":{\"SourceRef\":{\"Source\":\"m\"}},\"Property\":\"HTML Filter Panel\"},\"Name\":\"medidas.HTML Filter Panel\",\"NativeReferenceName\":\"HTML Filter Panel\"}]},\"hasDefaultSort\":true,\"objects\":{}}}",
          "filters": "[]",
          "height": 676.0,
          "width": 232.0,
          "x": 1024.0,
          "y": 20.0,
          "z": 50.0
        },
        {
          "config": "{\"name\":\"vab3ae55e5bec47a0882\",\"layouts\":[{\"id\":0,\"position\":{\"x\":1042,\"y\":164,\"z\":10000,\"width\":196,\"height\":58,\"tabOrder\":10000}}],\"singleVisual\":{\"visualType\":\"slicer\",\"drillFilterOtherVisuals\":true,\"projections\":{\"Values\":[{\"queryRef\":\"dim_calendario.Ano\",\"active\":true}]},\"prototypeQuery\":{\"Version\":2,\"From\":[{\"Name\":\"d\",\"Entity\":\"dim_calendario\",\"Type\":0}],\"Select\":[{\"Column\":{\"Expression\":{\"SourceRef\":{\"Source\":\"d\"}},\"Property\":\"Ano\"},\"Name\":\"dim_calendario.Ano\",\"NativeReferenceName\":\"Ano\"}]},\"hasDefaultSort\":true,\"objects\":{\"title\":[{\"properties\":{\"text\":{\"expr\":{\"Literal\":{\"Value\":\"'Ano'\"}}}}}]}}}",
          "filters": "[]",
          "height": 58.0,
          "width": 196.0,
          "x": 1042.0,
          "y": 164.0,
          "z": 10000.0
        },
        {
          "config": "{\"name\":\"v224bef5aac5547de94e\",\"layouts\":[{\"id\":0,\"position\":{\"x\":1042,\"y\":234,\"z\":10001,\"width\":196,\"height\":58,\"tabOrder\":10001}}],\"singleVisual\":{\"visualType\":\"slicer\",\"drillFilterOtherVisuals\":true,\"projections\":{\"Values\":[{\"queryRef\":\"dim_calendario.Mes Nome\",\"active\":true}]},\"prototypeQuery\":{\"Version\":2,\"From\":[{\"Name\":\"d\",\"Entity\":\"dim_calendario\",\"Type\":0}],\"Select\":[{\"Column\":{\"Expression\":{\"SourceRef\":{\"Source\":\"d\"}},\"Property\":\"Mes Nome\"},\"Name\":\"dim_calendario.Mes Nome\",\"NativeReferenceName\":\"Mes Nome\"}]},\"hasDefaultSort\":true,\"objects\":{\"title\":[{\"properties\":{\"text\":{\"expr\":{\"Literal\":{\"Value\":\"'Mes'\"}}}}}]}}}",
          "filters": "[]",
          "height": 58.0,
          "width": 196.0,
          "x": 1042.0,
          "y": 234.0,
          "z": 10001.0
        },
        {
          "config": "{\"name\":\"v13bce4d6b9864abd843\",\"layouts\":[{\"id\":0,\"position\":{\"x\":1042,\"y\":304,\"z\":10002,\"width\":196,\"height\":58,\"tabOrder\":10002}}],\"singleVisual\":{\"visualType\":\"slicer\",\"drillFilterOtherVisuals\":true,\"projections\":{\"Values\":[{\"queryRef\":\"dim_categoria.nome_categoria\",\"active\":true}]},\"prototypeQuery\":{\"Version\":2,\"From\":[{\"Name\":\"c\",\"Entity\":\"dim_categoria\",\"Type\":0}],\"Select\":[{\"Column\":{\"Expression\":{\"SourceRef\":{\"Source\":\"c\"}},\"Property\":\"nome_categoria\"},\"Name\":\"dim_categoria.nome_categoria\",\"NativeReferenceName\":\"nome_categoria\"}]},\"hasDefaultSort\":true,\"objects\":{\"title\":[{\"properties\":{\"text\":{\"expr\":{\"Literal\":{\"Value\":\"'Categoria'\"}}}}}]}}}",
          "filters": "[]",
          "height": 58.0,
          "width": 196.0,
          "x": 1042.0,
          "y": 304.0,
          "z": 10002.0
        },
        {
          "config": "{\"name\":\"vd8db3b946c74401ab2c\",\"layouts\":[{\"id\":0,\"position\":{\"x\":1042,\"y\":374,\"z\":10003,\"width\":196,\"height\":58,\"tabOrder\":10003}}],\"singleVisual\":{\"visualType\":\"slicer\",\"drillFilterOtherVisuals\":true,\"projections\":{\"Values\":[{\"queryRef\":\"dim_forma_pagamento.forma\",\"active\":true}]},\"prototypeQuery\":{\"Version\":2,\"From\":[{\"Name\":\"p\",\"Entity\":\"dim_forma_pagamento\",\"Type\":0}],\"Select\":[{\"Column\":{\"Expression\":{\"SourceRef\":{\"Source\":\"p\"}},\"Property\":\"forma\"},\"Name\":\"dim_forma_pagamento.forma\",\"NativeReferenceName\":\"forma\"}]},\"hasDefaultSort\":true,\"objects\":{\"title\":[{\"properties\":{\"text\":{\"expr\":{\"Literal\":{\"Value\":\"'Forma'\"}}}}}]}}}",
          "filters": "[]",
          "height": 58.0,
          "width": 196.0,
          "x": 1042.0,
          "y": 374.0,
          "z": 10003.0
        },
        {
          "config": "{\"name\":\"va48583fed5fa4b03ac1\",\"layouts\":[{\"id\":0,\"position\":{\"x\":1042,\"y\":444,\"z\":10004,\"width\":196,\"height\":58,\"tabOrder\":10004}}],\"singleVisual\":{\"visualType\":\"slicer\",\"drillFilterOtherVisuals\":true,\"projections\":{\"Values\":[{\"queryRef\":\"fat_lancamentos_financeiros.tipo\",\"active\":true}]},\"prototypeQuery\":{\"Version\":2,\"From\":[{\"Name\":\"f\",\"Entity\":\"fat_lancamentos_financeiros\",\"Type\":0}],\"Select\":[{\"Column\":{\"Expression\":{\"SourceRef\":{\"Source\":\"f\"}},\"Property\":\"tipo\"},\"Name\":\"fat_lancamentos_financeiros.tipo\",\"NativeReferenceName\":\"tipo\"}]},\"hasDefaultSort\":true,\"objects\":{\"title\":[{\"properties\":{\"text\":{\"expr\":{\"Literal\":{\"Value\":\"'Tipo'\"}}}}}]}}}",
          "filters": "[]",
          "height": 58.0,
          "width": 196.0,
          "x": 1042.0,
          "y": 444.0,
          "z": 10004.0
        },
        {
          "config": "{\"name\":\"vceee338b788242489ef\",\"layouts\":[{\"id\":0,\"position\":{\"x\":24,\"y\":116,\"z\":1000,\"width\":239,\"height\":118,\"tabOrder\":1000}}],\"singleVisual\":{\"visualType\":\"htmlContent443BE3AD55E043BF878BED274D3A6865\",\"drillFilterOtherVisuals\":true,\"projections\":{\"content\":[{\"queryRef\":\"medidas.HTML KPI Receita\"}]},\"prototypeQuery\":{\"Version\":2,\"From\":[{\"Name\":\"m\",\"Entity\":\"medidas\",\"Type\":0}],\"Select\":[{\"Measure\":{\"Expression\":{\"SourceRef\":{\"Source\":\"m\"}},\"Property\":\"HTML KPI Receita\"},\"Name\":\"medidas.HTML KPI Receita\",\"NativeReferenceName\":\"HTML KPI Receita\"}]},\"hasDefaultSort\":true,\"objects\":{}}}",
          "filters": "[]",
          "height": 118.0,
          "width": 239.0,
          "x": 24.0,
          "y": 116.0,
          "z": 1000.0
        },
        {
          "config": "{\"name\":\"v530fc0e890714ab184e\",\"layouts\":[{\"id\":0,\"position\":{\"x\":277,\"y\":116,\"z\":1001,\"width\":239,\"height\":118,\"tabOrder\":1001}}],\"singleVisual\":{\"visualType\":\"htmlContent443BE3AD55E043BF878BED274D3A6865\",\"drillFilterOtherVisuals\":true,\"projections\":{\"content\":[{\"queryRef\":\"medidas.HTML KPI Receita Anterior\"}]},\"prototypeQuery\":{\"Version\":2,\"From\":[{\"Name\":\"m\",\"Entity\":\"medidas\",\"Type\":0}],\"Select\":[{\"Measure\":{\"Expression\":{\"SourceRef\":{\"Source\":\"m\"}},\"Property\":\"HTML KPI Receita Anterior\"},\"Name\":\"medidas.HTML KPI Receita Anterior\",\"NativeReferenceName\":\"HTML KPI Receita Anterior\"}]},\"hasDefaultSort\":true,\"objects\":{}}}",
          "filters": "[]",
          "height": 118.0,
          "width": 239.0,
          "x": 277.0,
          "y": 116.0,
          "z": 1001.0
        },
        {
          "config": "{\"name\":\"vaad9c032d5734d2cb2b\",\"layouts\":[{\"id\":0,\"position\":{\"x\":530,\"y\":116,\"z\":1002,\"width\":239,\"height\":118,\"tabOrder\":1002}}],\"singleVisual\":{\"visualType\":\"htmlContent443BE3AD55E043BF878BED274D3A6865\",\"drillFilterOtherVisuals\":true,\"projections\":{\"content\":[{\"queryRef\":\"medidas.HTML KPI Variacao Receita\"}]},\"prototypeQuery\":{\"Version\":2,\"From\":[{\"Name\":\"m\",\"Entity\":\"medidas\",\"Type\":0}],\"Select\":[{\"Measure\":{\"Expression\":{\"SourceRef\":{\"Source\":\"m\"}},\"Property\":\"HTML KPI Variacao Receita\"},\"Name\":\"medidas.HTML KPI Variacao Receita\",\"NativeReferenceName\":\"HTML KPI Variacao Receita\"}]},\"hasDefaultSort\":true,\"objects\":{}}}",
          "filters": "[]",
          "height": 118.0,
          "width": 239.0,
          "x": 530.0,
          "y": 116.0,
          "z": 1002.0
        },
        {
          "config": "{\"name\":\"v0daea1ae77b848d4935\",\"layouts\":[{\"id\":0,\"position\":{\"x\":783,\"y\":116,\"z\":1003,\"width\":239,\"height\":118,\"tabOrder\":1003}}],\"singleVisual\":{\"visualType\":\"htmlContent443BE3AD55E043BF878BED274D3A6865\",\"drillFilterOtherVisuals\":true,\"projections\":{\"content\":[{\"queryRef\":\"medidas.HTML KPI Ticket Medio\"}]},\"prototypeQuery\":{\"Version\":2,\"From\":[{\"Name\":\"m\",\"Entity\":\"medidas\",\"Type\":0}],\"Select\":[{\"Measure\":{\"Expression\":{\"SourceRef\":{\"Source\":\"m\"}},\"Property\":\"HTML KPI Ticket Medio\"},\"Name\":\"medidas.HTML KPI Ticket Medio\",\"NativeReferenceName\":\"HTML KPI Ticket Medio\"}]},\"hasDefaultSort\":true,\"objects\":{}}}",
          "filters": "[]",
          "height": 118.0,
          "width": 239.0,
          "x": 783.0,
          "y": 116.0,
          "z": 1003.0
        },
        {
          "config": "{\"name\":\"v0d2c2c829d1045eca16\",\"layouts\":[{\"id\":0,\"position\":{\"x\":24,\"y\":256,\"z\":2000,\"width\":470,\"height\":218,\"tabOrder\":2000}}],\"singleVisual\":{\"visualType\":\"clusteredColumnChart\",\"drillFilterOtherVisuals\":true,\"projections\":{\"Category\":[{\"queryRef\":\"dim_calendario.Ano Mes\",\"active\":true}],\"Y\":[{\"queryRef\":\"medidas.Receita Total\"}],\"Tooltips\":[{\"queryRef\":\"medidas.Receita Total\"},{\"queryRef\":\"medidas.Despesa Total\"},{\"queryRef\":\"medidas.Resultado\"},{\"queryRef\":\"medidas.Margem de Resultado %\"}]},\"prototypeQuery\":{\"Version\":2,\"From\":[{\"Name\":\"d\",\"Entity\":\"dim_calendario\",\"Type\":0},{\"Name\":\"m\",\"Entity\":\"medidas\",\"Type\":0}],\"Select\":[{\"Column\":{\"Expression\":{\"SourceRef\":{\"Source\":\"d\"}},\"Property\":\"Ano Mes\"},\"Name\":\"dim_calendario.Ano Mes\",\"NativeReferenceName\":\"Ano Mes\"},{\"Measure\":{\"Expression\":{\"SourceRef\":{\"Source\":\"m\"}},\"Property\":\"Receita Total\"},\"Name\":\"medidas.Receita Total\",\"NativeReferenceName\":\"Receita Total\"},{\"Measure\":{\"Expression\":{\"SourceRef\":{\"Source\":\"m\"}},\"Property\":\"Despesa Total\"},\"Name\":\"medidas.Despesa Total\",\"NativeReferenceName\":\"Despesa Total\"},{\"Measure\":{\"Expression\":{\"SourceRef\":{\"Source\":\"m\"}},\"Property\":\"Resultado\"},\"Name\":\"medidas.Resultado\",\"NativeReferenceName\":\"Resultado\"},{\"Measure\":{\"Expression\":{\"SourceRef\":{\"Source\":\"m\"}},\"Property\":\"Margem de Resultado %\"},\"Name\":\"medidas.Margem de Resultado %\",\"NativeReferenceName\":\"Margem de Resultado %\"}],\"OrderBy\":[{\"Direction\":1,\"Expression\":{\"Column\":{\"Expression\":{\"SourceRef\":{\"Source\":\"d\"}},\"Property\":\"Ano Mes\"}}}]},\"hasDefaultSort\":true,\"objects\":{\"title\":[{\"properties\":{\"text\":{\"expr\":{\"Literal\":{\"Value\":\"'Evolucao mensal'\"}}}}}]}}}",
          "filters": "[]",
          "height": 218.0,
          "width": 470.0,
          "x": 24.0,
          "y": 256.0,
          "z": 2000.0
        },
        {
          "config": "{\"name\":\"v3278129990044600879\",\"layouts\":[{\"id\":0,\"position\":{\"x\":514,\"y\":256,\"z\":2001,\"width\":490,\"height\":218,\"tabOrder\":2001}}],\"singleVisual\":{\"visualType\":\"lineChart\",\"drillFilterOtherVisuals\":true,\"projections\":{\"Category\":[{\"queryRef\":\"dim_calendario.Ano Mes\",\"active\":true}],\"Y\":[{\"queryRef\":\"medidas.Receita Acumulada\"}],\"Tooltips\":[{\"queryRef\":\"medidas.Receita Total\"},{\"queryRef\":\"medidas.Despesa Total\"},{\"queryRef\":\"medidas.Resultado\"},{\"queryRef\":\"medidas.Margem de Resultado %\"}]},\"prototypeQuery\":{\"Version\":2,\"From\":[{\"Name\":\"d\",\"Entity\":\"dim_calendario\",\"Type\":0},{\"Name\":\"m\",\"Entity\":\"medidas\",\"Type\":0}],\"Select\":[{\"Column\":{\"Expression\":{\"SourceRef\":{\"Source\":\"d\"}},\"Property\":\"Ano Mes\"},\"Name\":\"dim_calendario.Ano Mes\",\"NativeReferenceName\":\"Ano Mes\"},{\"Measure\":{\"Expression\":{\"SourceRef\":{\"Source\":\"m\"}},\"Property\":\"Receita Acumulada\"},\"Name\":\"medidas.Receita Acumulada\",\"NativeReferenceName\":\"Receita Acumulada\"},{\"Measure\":{\"Expression\":{\"SourceRef\":{\"Source\":\"m\"}},\"Property\":\"Receita Total\"},\"Name\":\"medidas.Receita Total\",\"NativeReferenceName\":\"Receita Total\"},{\"Measure\":{\"Expression\":{\"SourceRef\":{\"Source\":\"m\"}},\"Property\":\"Despesa Total\"},\"Name\":\"medidas.Despesa Total\",\"NativeReferenceName\":\"Despesa Total\"},{\"Measure\":{\"Expression\":{\"SourceRef\":{\"Source\":\"m\"}},\"Property\":\"Resultado\"},\"Name\":\"medidas.Resultado\",\"NativeReferenceName\":\"Resultado\"},{\"Measure\":{\"Expression\":{\"SourceRef\":{\"Source\":\"m\"}},\"Property\":\"Margem de Resultado %\"},\"Name\":\"medidas.Margem de Resultado %\",\"NativeReferenceName\":\"Margem de Resultado %\"}],\"OrderBy\":[{\"Direction\":1,\"Expression\":{\"Column\":{\"Expression\":{\"SourceRef\":{\"Source\":\"d\"}},\"Property\":\"Ano Mes\"}}}]},\"hasDefaultSort\":true,\"objects\":{\"title\":[{\"properties\":{\"text\":{\"expr\":{\"Literal\":{\"Value\":\"'Receita acumulada'\"}}}}}]}}}",
          "filters": "[]",
          "height": 218.0,
          "width": 490.0,
          "x": 514.0,
          "y": 256.0,
          "z": 2001.0
        },
        {
          "config": "{\"name\":\"vc12dbcc8de4d4edd9e8\",\"layouts\":[{\"id\":0,\"position\":{\"x\":24,\"y\":498,\"z\":3000,\"width\":310,\"height\":198,\"tabOrder\":3000}}],\"singleVisual\":{\"visualType\":\"clusteredBarChart\",\"drillFilterOtherVisuals\":true,\"projections\":{\"Category\":[{\"queryRef\":\"dim_categoria.nome_categoria\",\"active\":true}],\"Y\":[{\"queryRef\":\"medidas.Receita Total\"}],\"Tooltips\":[{\"queryRef\":\"medidas.Receita Total\"},{\"queryRef\":\"medidas.Despesa Total\"},{\"queryRef\":\"medidas.Resultado\"},{\"queryRef\":\"medidas.Margem de Resultado %\"}]},\"prototypeQuery\":{\"Version\":2,\"From\":[{\"Name\":\"c\",\"Entity\":\"dim_categoria\",\"Type\":0},{\"Name\":\"m\",\"Entity\":\"medidas\",\"Type\":0}],\"Select\":[{\"Column\":{\"Expression\":{\"SourceRef\":{\"Source\":\"c\"}},\"Property\":\"nome_categoria\"},\"Name\":\"dim_categoria.nome_categoria\",\"NativeReferenceName\":\"nome_categoria\"},{\"Measure\":{\"Expression\":{\"SourceRef\":{\"Source\":\"m\"}},\"Property\":\"Receita Total\"},\"Name\":\"medidas.Receita Total\",\"NativeReferenceName\":\"Receita Total\"},{\"Measure\":{\"Expression\":{\"SourceRef\":{\"Source\":\"m\"}},\"Property\":\"Despesa Total\"},\"Name\":\"medidas.Despesa Total\",\"NativeReferenceName\":\"Despesa Total\"},{\"Measure\":{\"Expression\":{\"SourceRef\":{\"Source\":\"m\"}},\"Property\":\"Resultado\"},\"Name\":\"medidas.Resultado\",\"NativeReferenceName\":\"Resultado\"},{\"Measure\":{\"Expression\":{\"SourceRef\":{\"Source\":\"m\"}},\"Property\":\"Margem de Resultado %\"},\"Name\":\"medidas.Margem de Resultado %\",\"NativeReferenceName\":\"Margem de Resultado %\"}],\"OrderBy\":[{\"Direction\":2,\"Expression\":{\"Measure\":{\"Expression\":{\"SourceRef\":{\"Source\":\"m\"}},\"Property\":\"Receita Total\"}}}]},\"hasDefaultSort\":true,\"objects\":{\"title\":[{\"properties\":{\"text\":{\"expr\":{\"Literal\":{\"Value\":\"'Categorias de receita'\"}}}}}]}}}",
          "filters": "[]",
          "height": 198.0,
          "width": 310.0,
          "x": 24.0,
          "y": 498.0,
          "z": 3000.0
        },
        {
          "config": "{\"name\":\"v9bde6ab49d74429a939\",\"layouts\":[{\"id\":0,\"position\":{\"x\":354,\"y\":498,\"z\":3001,\"width\":300,\"height\":198,\"tabOrder\":3001}}],\"singleVisual\":{\"visualType\":\"donutChart\",\"drillFilterOtherVisuals\":true,\"projections\":{\"Category\":[{\"queryRef\":\"dim_forma_pagamento.forma\",\"active\":true}],\"Y\":[{\"queryRef\":\"medidas.Receita Total\"}],\"Tooltips\":[{\"queryRef\":\"medidas.Receita Total\"},{\"queryRef\":\"medidas.Despesa Total\"},{\"queryRef\":\"medidas.Resultado\"},{\"queryRef\":\"medidas.Margem de Resultado %\"}]},\"prototypeQuery\":{\"Version\":2,\"From\":[{\"Name\":\"p\",\"Entity\":\"dim_forma_pagamento\",\"Type\":0},{\"Name\":\"m\",\"Entity\":\"medidas\",\"Type\":0}],\"Select\":[{\"Column\":{\"Expression\":{\"SourceRef\":{\"Source\":\"p\"}},\"Property\":\"forma\"},\"Name\":\"dim_forma_pagamento.forma\",\"NativeReferenceName\":\"forma\"},{\"Measure\":{\"Expression\":{\"SourceRef\":{\"Source\":\"m\"}},\"Property\":\"Receita Total\"},\"Name\":\"medidas.Receita Total\",\"NativeReferenceName\":\"Receita Total\"},{\"Measure\":{\"Expression\":{\"SourceRef\":{\"Source\":\"m\"}},\"Property\":\"Despesa Total\"},\"Name\":\"medidas.Despesa Total\",\"NativeReferenceName\":\"Despesa Total\"},{\"Measure\":{\"Expression\":{\"SourceRef\":{\"Source\":\"m\"}},\"Property\":\"Resultado\"},\"Name\":\"medidas.Resultado\",\"NativeReferenceName\":\"Resultado\"},{\"Measure\":{\"Expression\":{\"SourceRef\":{\"Source\":\"m\"}},\"Property\":\"Margem de Resultado %\"},\"Name\":\"medidas.Margem de Resultado %\",\"NativeReferenceName\":\"Margem de Resultado %\"}],\"OrderBy\":[{\"Direction\":2,\"Expression\":{\"Measure\":{\"Expression\":{\"SourceRef\":{\"Source\":\"m\"}},\"Property\":\"Receita Total\"}}}]},\"hasDefaultSort\":true,\"objects\":{\"title\":[{\"properties\":{\"text\":{\"expr\":{\"Literal\":{\"Value\":\"'Forma de pagamento'\"}}}}}]}}}",
          "filters": "[]",
          "height": 198.0,
          "width": 300.0,
          "x": 354.0,
          "y": 498.0,
          "z": 3001.0
        },
        {
          "config": "{\"name\":\"v841bc7ed620c44adb4b\",\"layouts\":[{\"id\":0,\"position\":{\"x\":674,\"y\":498,\"z\":3002,\"width\":330,\"height\":198,\"tabOrder\":3002}}],\"singleVisual\":{\"visualType\":\"tableEx\",\"drillFilterOtherVisuals\":true,\"projections\":{\"Values\":[{\"queryRef\":\"fat_lancamentos_financeiros.data_lancamento\"},{\"queryRef\":\"fat_lancamentos_financeiros.descricao\"},{\"queryRef\":\"dim_categoria.nome_categoria\",\"active\":true},{\"queryRef\":\"dim_forma_pagamento.forma\",\"active\":true},{\"queryRef\":\"fat_lancamentos_financeiros.valor\"}]},\"prototypeQuery\":{\"Version\":2,\"From\":[{\"Name\":\"f\",\"Entity\":\"fat_lancamentos_financeiros\",\"Type\":0},{\"Name\":\"c\",\"Entity\":\"dim_categoria\",\"Type\":0},{\"Name\":\"p\",\"Entity\":\"dim_forma_pagamento\",\"Type\":0}],\"Select\":[{\"Column\":{\"Expression\":{\"SourceRef\":{\"Source\":\"f\"}},\"Property\":\"data_lancamento\"},\"Name\":\"fat_lancamentos_financeiros.data_lancamento\",\"NativeReferenceName\":\"data_lancamento\"},{\"Column\":{\"Expression\":{\"SourceRef\":{\"Source\":\"f\"}},\"Property\":\"descricao\"},\"Name\":\"fat_lancamentos_financeiros.descricao\",\"NativeReferenceName\":\"descricao\"},{\"Column\":{\"Expression\":{\"SourceRef\":{\"Source\":\"c\"}},\"Property\":\"nome_categoria\"},\"Name\":\"dim_categoria.nome_categoria\",\"NativeReferenceName\":\"nome_categoria\"},{\"Column\":{\"Expression\":{\"SourceRef\":{\"Source\":\"p\"}},\"Property\":\"forma\"},\"Name\":\"dim_forma_pagamento.forma\",\"NativeReferenceName\":\"forma\"},{\"Column\":{\"Expression\":{\"SourceRef\":{\"Source\":\"f\"}},\"Property\":\"valor\"},\"Name\":\"fat_lancamentos_financeiros.valor\",\"NativeReferenceName\":\"valor\"}],\"OrderBy\":[{\"Direction\":2,\"Expression\":{\"Column\":{\"Expression\":{\"SourceRef\":{\"Source\":\"f\"}},\"Property\":\"valor\"}}}]},\"hasDefaultSort\":true,\"objects\":{\"title\":[{\"properties\":{\"text\":{\"expr\":{\"Literal\":{\"Value\":\"'Maiores receitas'\"}}}}}]}}}",
          "filters": "[]",
          "height": 198.0,
          "width": 330.0,
          "x": 674.0,
          "y": 498.0,
          "z": 3002.0
        }
      ],
      "width": 1280.0
    },
    {
      "config": "{}",
      "displayName": "Despesas",
      "displayOption": 1,
      "filters": "[]",
      "height": 720.0,
      "name": "sec_despesas",
      "ordinal": 2,
      "visualContainers": [
        {
          "config": "{\"name\":\"vf26d91fa6f744bca93c\",\"layouts\":[{\"id\":0,\"position\":{\"x\":24,\"y\":20,\"z\":100,\"width\":540,\"height\":78,\"tabOrder\":100}}],\"singleVisual\":{\"visualType\":\"htmlContent443BE3AD55E043BF878BED274D3A6865\",\"drillFilterOtherVisuals\":true,\"projections\":{\"content\":[{\"queryRef\":\"medidas.HTML Header Despesas\"}]},\"prototypeQuery\":{\"Version\":2,\"From\":[{\"Name\":\"m\",\"Entity\":\"medidas\",\"Type\":0}],\"Select\":[{\"Measure\":{\"Expression\":{\"SourceRef\":{\"Source\":\"m\"}},\"Property\":\"HTML Header Despesas\"},\"Name\":\"medidas.HTML Header Despesas\",\"NativeReferenceName\":\"HTML Header Despesas\"}]},\"hasDefaultSort\":true,\"objects\":{}}}",
          "filters": "[]",
          "height": 78.0,
          "width": 540.0,
          "x": 24.0,
          "y": 20.0,
          "z": 100.0
        },
        {
          "config": "{\"name\":\"v136c2ddeb23c4155bf4\",\"layouts\":[{\"id\":0,\"position\":{\"x\":584,\"y\":37,\"z\":150,\"width\":420,\"height\":36,\"tabOrder\":150}}],\"singleVisual\":{\"visualType\":\"pageNavigator\",\"drillFilterOtherVisuals\":true}}",
          "filters": "[]",
          "height": 36.0,
          "width": 420.0,
          "x": 584.0,
          "y": 37.0,
          "z": 150.0
        },
        {
          "config": "{\"name\":\"v40f4f8191ec24141b39\",\"layouts\":[{\"id\":0,\"position\":{\"x\":1024,\"y\":20,\"z\":50,\"width\":232,\"height\":676,\"tabOrder\":50}}],\"singleVisual\":{\"visualType\":\"htmlContent443BE3AD55E043BF878BED274D3A6865\",\"drillFilterOtherVisuals\":true,\"projections\":{\"content\":[{\"queryRef\":\"medidas.HTML Filter Panel\"}]},\"prototypeQuery\":{\"Version\":2,\"From\":[{\"Name\":\"m\",\"Entity\":\"medidas\",\"Type\":0}],\"Select\":[{\"Measure\":{\"Expression\":{\"SourceRef\":{\"Source\":\"m\"}},\"Property\":\"HTML Filter Panel\"},\"Name\":\"medidas.HTML Filter Panel\",\"NativeReferenceName\":\"HTML Filter Panel\"}]},\"hasDefaultSort\":true,\"objects\":{}}}",
          "filters": "[]",
          "height": 676.0,
          "width": 232.0,
          "x": 1024.0,
          "y": 20.0,
          "z": 50.0
        },
        {
          "config": "{\"name\":\"ve1674d72409e4783ad7\",\"layouts\":[{\"id\":0,\"position\":{\"x\":1042,\"y\":164,\"z\":10000,\"width\":196,\"height\":58,\"tabOrder\":10000}}],\"singleVisual\":{\"visualType\":\"slicer\",\"drillFilterOtherVisuals\":true,\"projections\":{\"Values\":[{\"queryRef\":\"dim_calendario.Ano\",\"active\":true}]},\"prototypeQuery\":{\"Version\":2,\"From\":[{\"Name\":\"d\",\"Entity\":\"dim_calendario\",\"Type\":0}],\"Select\":[{\"Column\":{\"Expression\":{\"SourceRef\":{\"Source\":\"d\"}},\"Property\":\"Ano\"},\"Name\":\"dim_calendario.Ano\",\"NativeReferenceName\":\"Ano\"}]},\"hasDefaultSort\":true,\"objects\":{\"title\":[{\"properties\":{\"text\":{\"expr\":{\"Literal\":{\"Value\":\"'Ano'\"}}}}}]}}}",
          "filters": "[]",
          "height": 58.0,
          "width": 196.0,
          "x": 1042.0,
          "y": 164.0,
          "z": 10000.0
        },
        {
          "config": "{\"name\":\"v3ea526ebf6bc435d821\",\"layouts\":[{\"id\":0,\"position\":{\"x\":1042,\"y\":234,\"z\":10001,\"width\":196,\"height\":58,\"tabOrder\":10001}}],\"singleVisual\":{\"visualType\":\"slicer\",\"drillFilterOtherVisuals\":true,\"projections\":{\"Values\":[{\"queryRef\":\"dim_calendario.Mes Nome\",\"active\":true}]},\"prototypeQuery\":{\"Version\":2,\"From\":[{\"Name\":\"d\",\"Entity\":\"dim_calendario\",\"Type\":0}],\"Select\":[{\"Column\":{\"Expression\":{\"SourceRef\":{\"Source\":\"d\"}},\"Property\":\"Mes Nome\"},\"Name\":\"dim_calendario.Mes Nome\",\"NativeReferenceName\":\"Mes Nome\"}]},\"hasDefaultSort\":true,\"objects\":{\"title\":[{\"properties\":{\"text\":{\"expr\":{\"Literal\":{\"Value\":\"'Mes'\"}}}}}]}}}",
          "filters": "[]",
          "height": 58.0,
          "width": 196.0,
          "x": 1042.0,
          "y": 234.0,
          "z": 10001.0
        },
        {
          "config": "{\"name\":\"v008ad990be04414c88c\",\"layouts\":[{\"id\":0,\"position\":{\"x\":1042,\"y\":304,\"z\":10002,\"width\":196,\"height\":58,\"tabOrder\":10002}}],\"singleVisual\":{\"visualType\":\"slicer\",\"drillFilterOtherVisuals\":true,\"projections\":{\"Values\":[{\"queryRef\":\"dim_categoria.nome_categoria\",\"active\":true}]},\"prototypeQuery\":{\"Version\":2,\"From\":[{\"Name\":\"c\",\"Entity\":\"dim_categoria\",\"Type\":0}],\"Select\":[{\"Column\":{\"Expression\":{\"SourceRef\":{\"Source\":\"c\"}},\"Property\":\"nome_categoria\"},\"Name\":\"dim_categoria.nome_categoria\",\"NativeReferenceName\":\"nome_categoria\"}]},\"hasDefaultSort\":true,\"objects\":{\"title\":[{\"properties\":{\"text\":{\"expr\":{\"Literal\":{\"Value\":\"'Categoria'\"}}}}}]}}}",
          "filters": "[]",
          "height": 58.0,
          "width": 196.0,
          "x": 1042.0,
          "y": 304.0,
          "z": 10002.0
        },
        {
          "config": "{\"name\":\"v0e0d9aa192034f8d9fc\",\"layouts\":[{\"id\":0,\"position\":{\"x\":1042,\"y\":374,\"z\":10003,\"width\":196,\"height\":58,\"tabOrder\":10003}}],\"singleVisual\":{\"visualType\":\"slicer\",\"drillFilterOtherVisuals\":true,\"projections\":{\"Values\":[{\"queryRef\":\"dim_forma_pagamento.forma\",\"active\":true}]},\"prototypeQuery\":{\"Version\":2,\"From\":[{\"Name\":\"p\",\"Entity\":\"dim_forma_pagamento\",\"Type\":0}],\"Select\":[{\"Column\":{\"Expression\":{\"SourceRef\":{\"Source\":\"p\"}},\"Property\":\"forma\"},\"Name\":\"dim_forma_pagamento.forma\",\"NativeReferenceName\":\"forma\"}]},\"hasDefaultSort\":true,\"objects\":{\"title\":[{\"properties\":{\"text\":{\"expr\":{\"Literal\":{\"Value\":\"'Forma'\"}}}}}]}}}",
          "filters": "[]",
          "height": 58.0,
          "width": 196.0,
          "x": 1042.0,
          "y": 374.0,
          "z": 10003.0
        },
        {
          "config": "{\"name\":\"v57ff1630ff36478a896\",\"layouts\":[{\"id\":0,\"position\":{\"x\":1042,\"y\":444,\"z\":10004,\"width\":196,\"height\":58,\"tabOrder\":10004}}],\"singleVisual\":{\"visualType\":\"slicer\",\"drillFilterOtherVisuals\":true,\"projections\":{\"Values\":[{\"queryRef\":\"fat_lancamentos_financeiros.tipo\",\"active\":true}]},\"prototypeQuery\":{\"Version\":2,\"From\":[{\"Name\":\"f\",\"Entity\":\"fat_lancamentos_financeiros\",\"Type\":0}],\"Select\":[{\"Column\":{\"Expression\":{\"SourceRef\":{\"Source\":\"f\"}},\"Property\":\"tipo\"},\"Name\":\"fat_lancamentos_financeiros.tipo\",\"NativeReferenceName\":\"tipo\"}]},\"hasDefaultSort\":true,\"objects\":{\"title\":[{\"properties\":{\"text\":{\"expr\":{\"Literal\":{\"Value\":\"'Tipo'\"}}}}}]}}}",
          "filters": "[]",
          "height": 58.0,
          "width": 196.0,
          "x": 1042.0,
          "y": 444.0,
          "z": 10004.0
        },
        {
          "config": "{\"name\":\"v82fc1daae6e3427b864\",\"layouts\":[{\"id\":0,\"position\":{\"x\":24,\"y\":116,\"z\":1000,\"width\":239,\"height\":118,\"tabOrder\":1000}}],\"singleVisual\":{\"visualType\":\"htmlContent443BE3AD55E043BF878BED274D3A6865\",\"drillFilterOtherVisuals\":true,\"projections\":{\"content\":[{\"queryRef\":\"medidas.HTML KPI Despesa\"}]},\"prototypeQuery\":{\"Version\":2,\"From\":[{\"Name\":\"m\",\"Entity\":\"medidas\",\"Type\":0}],\"Select\":[{\"Measure\":{\"Expression\":{\"SourceRef\":{\"Source\":\"m\"}},\"Property\":\"HTML KPI Despesa\"},\"Name\":\"medidas.HTML KPI Despesa\",\"NativeReferenceName\":\"HTML KPI Despesa\"}]},\"hasDefaultSort\":true,\"objects\":{}}}",
          "filters": "[]",
          "height": 118.0,
          "width": 239.0,
          "x": 24.0,
          "y": 116.0,
          "z": 1000.0
        },
        {
          "config": "{\"name\":\"vc2b0576eee3245198ef\",\"layouts\":[{\"id\":0,\"position\":{\"x\":277,\"y\":116,\"z\":1001,\"width\":239,\"height\":118,\"tabOrder\":1001}}],\"singleVisual\":{\"visualType\":\"htmlContent443BE3AD55E043BF878BED274D3A6865\",\"drillFilterOtherVisuals\":true,\"projections\":{\"content\":[{\"queryRef\":\"medidas.HTML KPI Despesa Anterior\"}]},\"prototypeQuery\":{\"Version\":2,\"From\":[{\"Name\":\"m\",\"Entity\":\"medidas\",\"Type\":0}],\"Select\":[{\"Measure\":{\"Expression\":{\"SourceRef\":{\"Source\":\"m\"}},\"Property\":\"HTML KPI Despesa Anterior\"},\"Name\":\"medidas.HTML KPI Despesa Anterior\",\"NativeReferenceName\":\"HTML KPI Despesa Anterior\"}]},\"hasDefaultSort\":true,\"objects\":{}}}",
          "filters": "[]",
          "height": 118.0,
          "width": 239.0,
          "x": 277.0,
          "y": 116.0,
          "z": 1001.0
        },
        {
          "config": "{\"name\":\"veefe054e48724a64a76\",\"layouts\":[{\"id\":0,\"position\":{\"x\":530,\"y\":116,\"z\":1002,\"width\":239,\"height\":118,\"tabOrder\":1002}}],\"singleVisual\":{\"visualType\":\"htmlContent443BE3AD55E043BF878BED274D3A6865\",\"drillFilterOtherVisuals\":true,\"projections\":{\"content\":[{\"queryRef\":\"medidas.HTML KPI Variacao Despesa\"}]},\"prototypeQuery\":{\"Version\":2,\"From\":[{\"Name\":\"m\",\"Entity\":\"medidas\",\"Type\":0}],\"Select\":[{\"Measure\":{\"Expression\":{\"SourceRef\":{\"Source\":\"m\"}},\"Property\":\"HTML KPI Variacao Despesa\"},\"Name\":\"medidas.HTML KPI Variacao Despesa\",\"NativeReferenceName\":\"HTML KPI Variacao Despesa\"}]},\"hasDefaultSort\":true,\"objects\":{}}}",
          "filters": "[]",
          "height": 118.0,
          "width": 239.0,
          "x": 530.0,
          "y": 116.0,
          "z": 1002.0
        },
        {
          "config": "{\"name\":\"v6d7004b929e94fbb996\",\"layouts\":[{\"id\":0,\"position\":{\"x\":783,\"y\":116,\"z\":1003,\"width\":239,\"height\":118,\"tabOrder\":1003}}],\"singleVisual\":{\"visualType\":\"htmlContent443BE3AD55E043BF878BED274D3A6865\",\"drillFilterOtherVisuals\":true,\"projections\":{\"content\":[{\"queryRef\":\"medidas.HTML KPI Valor Medio\"}]},\"prototypeQuery\":{\"Version\":2,\"From\":[{\"Name\":\"m\",\"Entity\":\"medidas\",\"Type\":0}],\"Select\":[{\"Measure\":{\"Expression\":{\"SourceRef\":{\"Source\":\"m\"}},\"Property\":\"HTML KPI Valor Medio\"},\"Name\":\"medidas.HTML KPI Valor Medio\",\"NativeReferenceName\":\"HTML KPI Valor Medio\"}]},\"hasDefaultSort\":true,\"objects\":{}}}",
          "filters": "[]",
          "height": 118.0,
          "width": 239.0,
          "x": 783.0,
          "y": 116.0,
          "z": 1003.0
        },
        {
          "config": "{\"name\":\"ve4b87c82d64648bab63\",\"layouts\":[{\"id\":0,\"position\":{\"x\":24,\"y\":256,\"z\":2000,\"width\":470,\"height\":218,\"tabOrder\":2000}}],\"singleVisual\":{\"visualType\":\"clusteredColumnChart\",\"drillFilterOtherVisuals\":true,\"projections\":{\"Category\":[{\"queryRef\":\"dim_calendario.Ano Mes\",\"active\":true}],\"Y\":[{\"queryRef\":\"medidas.Despesa Total\"}],\"Tooltips\":[{\"queryRef\":\"medidas.Receita Total\"},{\"queryRef\":\"medidas.Despesa Total\"},{\"queryRef\":\"medidas.Resultado\"},{\"queryRef\":\"medidas.Margem de Resultado %\"}]},\"prototypeQuery\":{\"Version\":2,\"From\":[{\"Name\":\"d\",\"Entity\":\"dim_calendario\",\"Type\":0},{\"Name\":\"m\",\"Entity\":\"medidas\",\"Type\":0}],\"Select\":[{\"Column\":{\"Expression\":{\"SourceRef\":{\"Source\":\"d\"}},\"Property\":\"Ano Mes\"},\"Name\":\"dim_calendario.Ano Mes\",\"NativeReferenceName\":\"Ano Mes\"},{\"Measure\":{\"Expression\":{\"SourceRef\":{\"Source\":\"m\"}},\"Property\":\"Despesa Total\"},\"Name\":\"medidas.Despesa Total\",\"NativeReferenceName\":\"Despesa Total\"},{\"Measure\":{\"Expression\":{\"SourceRef\":{\"Source\":\"m\"}},\"Property\":\"Receita Total\"},\"Name\":\"medidas.Receita Total\",\"NativeReferenceName\":\"Receita Total\"},{\"Measure\":{\"Expression\":{\"SourceRef\":{\"Source\":\"m\"}},\"Property\":\"Resultado\"},\"Name\":\"medidas.Resultado\",\"NativeReferenceName\":\"Resultado\"},{\"Measure\":{\"Expression\":{\"SourceRef\":{\"Source\":\"m\"}},\"Property\":\"Margem de Resultado %\"},\"Name\":\"medidas.Margem de Resultado %\",\"NativeReferenceName\":\"Margem de Resultado %\"}],\"OrderBy\":[{\"Direction\":1,\"Expression\":{\"Column\":{\"Expression\":{\"SourceRef\":{\"Source\":\"d\"}},\"Property\":\"Ano Mes\"}}}]},\"hasDefaultSort\":true,\"objects\":{\"title\":[{\"properties\":{\"text\":{\"expr\":{\"Literal\":{\"Value\":\"'Evolucao mensal'\"}}}}}]}}}",
          "filters": "[]",
          "height": 218.0,
          "width": 470.0,
          "x": 24.0,
          "y": 256.0,
          "z": 2000.0
        },
        {
          "config": "{\"name\":\"v4234debd86c940d8b70\",\"layouts\":[{\"id\":0,\"position\":{\"x\":514,\"y\":256,\"z\":2001,\"width\":490,\"height\":218,\"tabOrder\":2001}}],\"singleVisual\":{\"visualType\":\"lineChart\",\"drillFilterOtherVisuals\":true,\"projections\":{\"Category\":[{\"queryRef\":\"dim_calendario.Ano Mes\",\"active\":true}],\"Y\":[{\"queryRef\":\"medidas.Despesa Acumulada\"}],\"Tooltips\":[{\"queryRef\":\"medidas.Receita Total\"},{\"queryRef\":\"medidas.Despesa Total\"},{\"queryRef\":\"medidas.Resultado\"},{\"queryRef\":\"medidas.Margem de Resultado %\"}]},\"prototypeQuery\":{\"Version\":2,\"From\":[{\"Name\":\"d\",\"Entity\":\"dim_calendario\",\"Type\":0},{\"Name\":\"m\",\"Entity\":\"medidas\",\"Type\":0}],\"Select\":[{\"Column\":{\"Expression\":{\"SourceRef\":{\"Source\":\"d\"}},\"Property\":\"Ano Mes\"},\"Name\":\"dim_calendario.Ano Mes\",\"NativeReferenceName\":\"Ano Mes\"},{\"Measure\":{\"Expression\":{\"SourceRef\":{\"Source\":\"m\"}},\"Property\":\"Despesa Acumulada\"},\"Name\":\"medidas.Despesa Acumulada\",\"NativeReferenceName\":\"Despesa Acumulada\"},{\"Measure\":{\"Expression\":{\"SourceRef\":{\"Source\":\"m\"}},\"Property\":\"Receita Total\"},\"Name\":\"medidas.Receita Total\",\"NativeReferenceName\":\"Receita Total\"},{\"Measure\":{\"Expression\":{\"SourceRef\":{\"Source\":\"m\"}},\"Property\":\"Despesa Total\"},\"Name\":\"medidas.Despesa Total\",\"NativeReferenceName\":\"Despesa Total\"},{\"Measure\":{\"Expression\":{\"SourceRef\":{\"Source\":\"m\"}},\"Property\":\"Resultado\"},\"Name\":\"medidas.Resultado\",\"NativeReferenceName\":\"Resultado\"},{\"Measure\":{\"Expression\":{\"SourceRef\":{\"Source\":\"m\"}},\"Property\":\"Margem de Resultado %\"},\"Name\":\"medidas.Margem de Resultado %\",\"NativeReferenceName\":\"Margem de Resultado %\"}],\"OrderBy\":[{\"Direction\":1,\"Expression\":{\"Column\":{\"Expression\":{\"SourceRef\":{\"Source\":\"d\"}},\"Property\":\"Ano Mes\"}}}]},\"hasDefaultSort\":true,\"objects\":{\"title\":[{\"properties\":{\"text\":{\"expr\":{\"Literal\":{\"Value\":\"'Despesa acumulada'\"}}}}}]}}}",
          "filters": "[]",
          "height": 218.0,
          "width": 490.0,
          "x": 514.0,
          "y": 256.0,
          "z": 2001.0
        },
        {
          "config": "{\"name\":\"v550135256c81423cafd\",\"layouts\":[{\"id\":0,\"position\":{\"x\":24,\"y\":498,\"z\":3000,\"width\":310,\"height\":198,\"tabOrder\":3000}}],\"singleVisual\":{\"visualType\":\"clusteredBarChart\",\"drillFilterOtherVisuals\":true,\"projections\":{\"Category\":[{\"queryRef\":\"dim_categoria.nome_categoria\",\"active\":true}],\"Y\":[{\"queryRef\":\"medidas.Despesa Total\"}],\"Tooltips\":[{\"queryRef\":\"medidas.Receita Total\"},{\"queryRef\":\"medidas.Despesa Total\"},{\"queryRef\":\"medidas.Resultado\"},{\"queryRef\":\"medidas.Margem de Resultado %\"}]},\"prototypeQuery\":{\"Version\":2,\"From\":[{\"Name\":\"c\",\"Entity\":\"dim_categoria\",\"Type\":0},{\"Name\":\"m\",\"Entity\":\"medidas\",\"Type\":0}],\"Select\":[{\"Column\":{\"Expression\":{\"SourceRef\":{\"Source\":\"c\"}},\"Property\":\"nome_categoria\"},\"Name\":\"dim_categoria.nome_categoria\",\"NativeReferenceName\":\"nome_categoria\"},{\"Measure\":{\"Expression\":{\"SourceRef\":{\"Source\":\"m\"}},\"Property\":\"Despesa Total\"},\"Name\":\"medidas.Despesa Total\",\"NativeReferenceName\":\"Despesa Total\"},{\"Measure\":{\"Expression\":{\"SourceRef\":{\"Source\":\"m\"}},\"Property\":\"Receita Total\"},\"Name\":\"medidas.Receita Total\",\"NativeReferenceName\":\"Receita Total\"},{\"Measure\":{\"Expression\":{\"SourceRef\":{\"Source\":\"m\"}},\"Property\":\"Resultado\"},\"Name\":\"medidas.Resultado\",\"NativeReferenceName\":\"Resultado\"},{\"Measure\":{\"Expression\":{\"SourceRef\":{\"Source\":\"m\"}},\"Property\":\"Margem de Resultado %\"},\"Name\":\"medidas.Margem de Resultado %\",\"NativeReferenceName\":\"Margem de Resultado %\"}],\"OrderBy\":[{\"Direction\":2,\"Expression\":{\"Measure\":{\"Expression\":{\"SourceRef\":{\"Source\":\"m\"}},\"Property\":\"Despesa Total\"}}}]},\"hasDefaultSort\":true,\"objects\":{\"title\":[{\"properties\":{\"text\":{\"expr\":{\"Literal\":{\"Value\":\"'Categorias de despesa'\"}}}}}]}}}",
          "filters": "[]",
          "height": 198.0,
          "width": 310.0,
          "x": 24.0,
          "y": 498.0,
          "z": 3000.0
        },
        {
          "config": "{\"name\":\"v0f384aef27954d23ab0\",\"layouts\":[{\"id\":0,\"position\":{\"x\":354,\"y\":498,\"z\":3001,\"width\":300,\"height\":198,\"tabOrder\":3001}}],\"singleVisual\":{\"visualType\":\"donutChart\",\"drillFilterOtherVisuals\":true,\"projections\":{\"Category\":[{\"queryRef\":\"dim_forma_pagamento.forma\",\"active\":true}],\"Y\":[{\"queryRef\":\"medidas.Despesa Total\"}],\"Tooltips\":[{\"queryRef\":\"medidas.Receita Total\"},{\"queryRef\":\"medidas.Despesa Total\"},{\"queryRef\":\"medidas.Resultado\"},{\"queryRef\":\"medidas.Margem de Resultado %\"}]},\"prototypeQuery\":{\"Version\":2,\"From\":[{\"Name\":\"p\",\"Entity\":\"dim_forma_pagamento\",\"Type\":0},{\"Name\":\"m\",\"Entity\":\"medidas\",\"Type\":0}],\"Select\":[{\"Column\":{\"Expression\":{\"SourceRef\":{\"Source\":\"p\"}},\"Property\":\"forma\"},\"Name\":\"dim_forma_pagamento.forma\",\"NativeReferenceName\":\"forma\"},{\"Measure\":{\"Expression\":{\"SourceRef\":{\"Source\":\"m\"}},\"Property\":\"Despesa Total\"},\"Name\":\"medidas.Despesa Total\",\"NativeReferenceName\":\"Despesa Total\"},{\"Measure\":{\"Expression\":{\"SourceRef\":{\"Source\":\"m\"}},\"Property\":\"Receita Total\"},\"Name\":\"medidas.Receita Total\",\"NativeReferenceName\":\"Receita Total\"},{\"Measure\":{\"Expression\":{\"SourceRef\":{\"Source\":\"m\"}},\"Property\":\"Resultado\"},\"Name\":\"medidas.Resultado\",\"NativeReferenceName\":\"Resultado\"},{\"Measure\":{\"Expression\":{\"SourceRef\":{\"Source\":\"m\"}},\"Property\":\"Margem de Resultado %\"},\"Name\":\"medidas.Margem de Resultado %\",\"NativeReferenceName\":\"Margem de Resultado %\"}],\"OrderBy\":[{\"Direction\":2,\"Expression\":{\"Measure\":{\"Expression\":{\"SourceRef\":{\"Source\":\"m\"}},\"Property\":\"Despesa Total\"}}}]},\"hasDefaultSort\":true,\"objects\":{\"title\":[{\"properties\":{\"text\":{\"expr\":{\"Literal\":{\"Value\":\"'Forma de pagamento'\"}}}}}]}}}",
          "filters": "[]",
          "height": 198.0,
          "width": 300.0,
          "x": 354.0,
          "y": 498.0,
          "z": 3001.0
        },
        {
          "config": "{\"name\":\"v4e142dbe184844ebab9\",\"layouts\":[{\"id\":0,\"position\":{\"x\":674,\"y\":498,\"z\":3002,\"width\":330,\"height\":198,\"tabOrder\":3002}}],\"singleVisual\":{\"visualType\":\"tableEx\",\"drillFilterOtherVisuals\":true,\"projections\":{\"Values\":[{\"queryRef\":\"fat_lancamentos_financeiros.data_lancamento\"},{\"queryRef\":\"fat_lancamentos_financeiros.descricao\"},{\"queryRef\":\"dim_categoria.nome_categoria\",\"active\":true},{\"queryRef\":\"dim_forma_pagamento.forma\",\"active\":true},{\"queryRef\":\"fat_lancamentos_financeiros.valor\"}]},\"prototypeQuery\":{\"Version\":2,\"From\":[{\"Name\":\"f\",\"Entity\":\"fat_lancamentos_financeiros\",\"Type\":0},{\"Name\":\"c\",\"Entity\":\"dim_categoria\",\"Type\":0},{\"Name\":\"p\",\"Entity\":\"dim_forma_pagamento\",\"Type\":0}],\"Select\":[{\"Column\":{\"Expression\":{\"SourceRef\":{\"Source\":\"f\"}},\"Property\":\"data_lancamento\"},\"Name\":\"fat_lancamentos_financeiros.data_lancamento\",\"NativeReferenceName\":\"data_lancamento\"},{\"Column\":{\"Expression\":{\"SourceRef\":{\"Source\":\"f\"}},\"Property\":\"descricao\"},\"Name\":\"fat_lancamentos_financeiros.descricao\",\"NativeReferenceName\":\"descricao\"},{\"Column\":{\"Expression\":{\"SourceRef\":{\"Source\":\"c\"}},\"Property\":\"nome_categoria\"},\"Name\":\"dim_categoria.nome_categoria\",\"NativeReferenceName\":\"nome_categoria\"},{\"Column\":{\"Expression\":{\"SourceRef\":{\"Source\":\"p\"}},\"Property\":\"forma\"},\"Name\":\"dim_forma_pagamento.forma\",\"NativeReferenceName\":\"forma\"},{\"Column\":{\"Expression\":{\"SourceRef\":{\"Source\":\"f\"}},\"Property\":\"valor\"},\"Name\":\"fat_lancamentos_financeiros.valor\",\"NativeReferenceName\":\"valor\"}],\"OrderBy\":[{\"Direction\":2,\"Expression\":{\"Column\":{\"Expression\":{\"SourceRef\":{\"Source\":\"f\"}},\"Property\":\"valor\"}}}]},\"hasDefaultSort\":true,\"objects\":{\"title\":[{\"properties\":{\"text\":{\"expr\":{\"Literal\":{\"Value\":\"'Maiores despesas'\"}}}}}]}}}",
          "filters": "[]",
          "height": 198.0,
          "width": 330.0,
          "x": 674.0,
          "y": 498.0,
          "z": 3002.0
        }
      ],
      "width": 1280.0
    },
    {
      "config": "{}",
      "displayName": "Resultado Financeiro",
      "displayOption": 1,
      "filters": "[]",
      "height": 720.0,
      "name": "sec_resultado",
      "ordinal": 3,
      "visualContainers": [
        {
          "config": "{\"name\":\"v9fe6f732bd0445da80c\",\"layouts\":[{\"id\":0,\"position\":{\"x\":24,\"y\":20,\"z\":100,\"width\":540,\"height\":78,\"tabOrder\":100}}],\"singleVisual\":{\"visualType\":\"htmlContent443BE3AD55E043BF878BED274D3A6865\",\"drillFilterOtherVisuals\":true,\"projections\":{\"content\":[{\"queryRef\":\"medidas.HTML Header Resultado\"}]},\"prototypeQuery\":{\"Version\":2,\"From\":[{\"Name\":\"m\",\"Entity\":\"medidas\",\"Type\":0}],\"Select\":[{\"Measure\":{\"Expression\":{\"SourceRef\":{\"Source\":\"m\"}},\"Property\":\"HTML Header Resultado\"},\"Name\":\"medidas.HTML Header Resultado\",\"NativeReferenceName\":\"HTML Header Resultado\"}]},\"hasDefaultSort\":true,\"objects\":{}}}",
          "filters": "[]",
          "height": 78.0,
          "width": 540.0,
          "x": 24.0,
          "y": 20.0,
          "z": 100.0
        },
        {
          "config": "{\"name\":\"v4308b9e9f2d04498835\",\"layouts\":[{\"id\":0,\"position\":{\"x\":584,\"y\":37,\"z\":150,\"width\":420,\"height\":36,\"tabOrder\":150}}],\"singleVisual\":{\"visualType\":\"pageNavigator\",\"drillFilterOtherVisuals\":true}}",
          "filters": "[]",
          "height": 36.0,
          "width": 420.0,
          "x": 584.0,
          "y": 37.0,
          "z": 150.0
        },
        {
          "config": "{\"name\":\"v247f76344e7246038a0\",\"layouts\":[{\"id\":0,\"position\":{\"x\":1024,\"y\":20,\"z\":50,\"width\":232,\"height\":676,\"tabOrder\":50}}],\"singleVisual\":{\"visualType\":\"htmlContent443BE3AD55E043BF878BED274D3A6865\",\"drillFilterOtherVisuals\":true,\"projections\":{\"content\":[{\"queryRef\":\"medidas.HTML Filter Panel\"}]},\"prototypeQuery\":{\"Version\":2,\"From\":[{\"Name\":\"m\",\"Entity\":\"medidas\",\"Type\":0}],\"Select\":[{\"Measure\":{\"Expression\":{\"SourceRef\":{\"Source\":\"m\"}},\"Property\":\"HTML Filter Panel\"},\"Name\":\"medidas.HTML Filter Panel\",\"NativeReferenceName\":\"HTML Filter Panel\"}]},\"hasDefaultSort\":true,\"objects\":{}}}",
          "filters": "[]",
          "height": 676.0,
          "width": 232.0,
          "x": 1024.0,
          "y": 20.0,
          "z": 50.0
        },
        {
          "config": "{\"name\":\"v511880bb6cae47328ff\",\"layouts\":[{\"id\":0,\"position\":{\"x\":1042,\"y\":164,\"z\":10000,\"width\":196,\"height\":58,\"tabOrder\":10000}}],\"singleVisual\":{\"visualType\":\"slicer\",\"drillFilterOtherVisuals\":true,\"projections\":{\"Values\":[{\"queryRef\":\"dim_calendario.Ano\",\"active\":true}]},\"prototypeQuery\":{\"Version\":2,\"From\":[{\"Name\":\"d\",\"Entity\":\"dim_calendario\",\"Type\":0}],\"Select\":[{\"Column\":{\"Expression\":{\"SourceRef\":{\"Source\":\"d\"}},\"Property\":\"Ano\"},\"Name\":\"dim_calendario.Ano\",\"NativeReferenceName\":\"Ano\"}]},\"hasDefaultSort\":true,\"objects\":{\"title\":[{\"properties\":{\"text\":{\"expr\":{\"Literal\":{\"Value\":\"'Ano'\"}}}}}]}}}",
          "filters": "[]",
          "height": 58.0,
          "width": 196.0,
          "x": 1042.0,
          "y": 164.0,
          "z": 10000.0
        },
        {
          "config": "{\"name\":\"ve8177a1e166e4f35925\",\"layouts\":[{\"id\":0,\"position\":{\"x\":1042,\"y\":234,\"z\":10001,\"width\":196,\"height\":58,\"tabOrder\":10001}}],\"singleVisual\":{\"visualType\":\"slicer\",\"drillFilterOtherVisuals\":true,\"projections\":{\"Values\":[{\"queryRef\":\"dim_calendario.Mes Nome\",\"active\":true}]},\"prototypeQuery\":{\"Version\":2,\"From\":[{\"Name\":\"d\",\"Entity\":\"dim_calendario\",\"Type\":0}],\"Select\":[{\"Column\":{\"Expression\":{\"SourceRef\":{\"Source\":\"d\"}},\"Property\":\"Mes Nome\"},\"Name\":\"dim_calendario.Mes Nome\",\"NativeReferenceName\":\"Mes Nome\"}]},\"hasDefaultSort\":true,\"objects\":{\"title\":[{\"properties\":{\"text\":{\"expr\":{\"Literal\":{\"Value\":\"'Mes'\"}}}}}]}}}",
          "filters": "[]",
          "height": 58.0,
          "width": 196.0,
          "x": 1042.0,
          "y": 234.0,
          "z": 10001.0
        },
        {
          "config": "{\"name\":\"v5a4349552fba4524973\",\"layouts\":[{\"id\":0,\"position\":{\"x\":1042,\"y\":304,\"z\":10002,\"width\":196,\"height\":58,\"tabOrder\":10002}}],\"singleVisual\":{\"visualType\":\"slicer\",\"drillFilterOtherVisuals\":true,\"projections\":{\"Values\":[{\"queryRef\":\"dim_categoria.nome_categoria\",\"active\":true}]},\"prototypeQuery\":{\"Version\":2,\"From\":[{\"Name\":\"c\",\"Entity\":\"dim_categoria\",\"Type\":0}],\"Select\":[{\"Column\":{\"Expression\":{\"SourceRef\":{\"Source\":\"c\"}},\"Property\":\"nome_categoria\"},\"Name\":\"dim_categoria.nome_categoria\",\"NativeReferenceName\":\"nome_categoria\"}]},\"hasDefaultSort\":true,\"objects\":{\"title\":[{\"properties\":{\"text\":{\"expr\":{\"Literal\":{\"Value\":\"'Categoria'\"}}}}}]}}}",
          "filters": "[]",
          "height": 58.0,
          "width": 196.0,
          "x": 1042.0,
          "y": 304.0,
          "z": 10002.0
        },
        {
          "config": "{\"name\":\"vde293d8bcea049558e2\",\"layouts\":[{\"id\":0,\"position\":{\"x\":1042,\"y\":374,\"z\":10003,\"width\":196,\"height\":58,\"tabOrder\":10003}}],\"singleVisual\":{\"visualType\":\"slicer\",\"drillFilterOtherVisuals\":true,\"projections\":{\"Values\":[{\"queryRef\":\"dim_forma_pagamento.forma\",\"active\":true}]},\"prototypeQuery\":{\"Version\":2,\"From\":[{\"Name\":\"p\",\"Entity\":\"dim_forma_pagamento\",\"Type\":0}],\"Select\":[{\"Column\":{\"Expression\":{\"SourceRef\":{\"Source\":\"p\"}},\"Property\":\"forma\"},\"Name\":\"dim_forma_pagamento.forma\",\"NativeReferenceName\":\"forma\"}]},\"hasDefaultSort\":true,\"objects\":{\"title\":[{\"properties\":{\"text\":{\"expr\":{\"Literal\":{\"Value\":\"'Forma'\"}}}}}]}}}",
          "filters": "[]",
          "height": 58.0,
          "width": 196.0,
          "x": 1042.0,
          "y": 374.0,
          "z": 10003.0
        },
        {
          "config": "{\"name\":\"v148d8ea46445401dac2\",\"layouts\":[{\"id\":0,\"position\":{\"x\":1042,\"y\":444,\"z\":10004,\"width\":196,\"height\":58,\"tabOrder\":10004}}],\"singleVisual\":{\"visualType\":\"slicer\",\"drillFilterOtherVisuals\":true,\"projections\":{\"Values\":[{\"queryRef\":\"fat_lancamentos_financeiros.tipo\",\"active\":true}]},\"prototypeQuery\":{\"Version\":2,\"From\":[{\"Name\":\"f\",\"Entity\":\"fat_lancamentos_financeiros\",\"Type\":0}],\"Select\":[{\"Column\":{\"Expression\":{\"SourceRef\":{\"Source\":\"f\"}},\"Property\":\"tipo\"},\"Name\":\"fat_lancamentos_financeiros.tipo\",\"NativeReferenceName\":\"tipo\"}]},\"hasDefaultSort\":true,\"objects\":{\"title\":[{\"properties\":{\"text\":{\"expr\":{\"Literal\":{\"Value\":\"'Tipo'\"}}}}}]}}}",
          "filters": "[]",
          "height": 58.0,
          "width": 196.0,
          "x": 1042.0,
          "y": 444.0,
          "z": 10004.0
        },
        {
          "config": "{\"name\":\"v47d9c3d2de99487daee\",\"layouts\":[{\"id\":0,\"position\":{\"x\":24,\"y\":116,\"z\":1000,\"width\":239,\"height\":118,\"tabOrder\":1000}}],\"singleVisual\":{\"visualType\":\"htmlContent443BE3AD55E043BF878BED274D3A6865\",\"drillFilterOtherVisuals\":true,\"projections\":{\"content\":[{\"queryRef\":\"medidas.HTML KPI Resultado\"}]},\"prototypeQuery\":{\"Version\":2,\"From\":[{\"Name\":\"m\",\"Entity\":\"medidas\",\"Type\":0}],\"Select\":[{\"Measure\":{\"Expression\":{\"SourceRef\":{\"Source\":\"m\"}},\"Property\":\"HTML KPI Resultado\"},\"Name\":\"medidas.HTML KPI Resultado\",\"NativeReferenceName\":\"HTML KPI Resultado\"}]},\"hasDefaultSort\":true,\"objects\":{}}}",
          "filters": "[]",
          "height": 118.0,
          "width": 239.0,
          "x": 24.0,
          "y": 116.0,
          "z": 1000.0
        },
        {
          "config": "{\"name\":\"v06c95962d1fc4345a2a\",\"layouts\":[{\"id\":0,\"position\":{\"x\":277,\"y\":116,\"z\":1001,\"width\":239,\"height\":118,\"tabOrder\":1001}}],\"singleVisual\":{\"visualType\":\"htmlContent443BE3AD55E043BF878BED274D3A6865\",\"drillFilterOtherVisuals\":true,\"projections\":{\"content\":[{\"queryRef\":\"medidas.HTML KPI Resultado Anterior\"}]},\"prototypeQuery\":{\"Version\":2,\"From\":[{\"Name\":\"m\",\"Entity\":\"medidas\",\"Type\":0}],\"Select\":[{\"Measure\":{\"Expression\":{\"SourceRef\":{\"Source\":\"m\"}},\"Property\":\"HTML KPI Resultado Anterior\"},\"Name\":\"medidas.HTML KPI Resultado Anterior\",\"NativeReferenceName\":\"HTML KPI Resultado Anterior\"}]},\"hasDefaultSort\":true,\"objects\":{}}}",
          "filters": "[]",
          "height": 118.0,
          "width": 239.0,
          "x": 277.0,
          "y": 116.0,
          "z": 1001.0
        },
        {
          "config": "{\"name\":\"vda9f852c76de497cbcf\",\"layouts\":[{\"id\":0,\"position\":{\"x\":530,\"y\":116,\"z\":1002,\"width\":239,\"height\":118,\"tabOrder\":1002}}],\"singleVisual\":{\"visualType\":\"htmlContent443BE3AD55E043BF878BED274D3A6865\",\"drillFilterOtherVisuals\":true,\"projections\":{\"content\":[{\"queryRef\":\"medidas.HTML KPI Variacao Resultado\"}]},\"prototypeQuery\":{\"Version\":2,\"From\":[{\"Name\":\"m\",\"Entity\":\"medidas\",\"Type\":0}],\"Select\":[{\"Measure\":{\"Expression\":{\"SourceRef\":{\"Source\":\"m\"}},\"Property\":\"HTML KPI Variacao Resultado\"},\"Name\":\"medidas.HTML KPI Variacao Resultado\",\"NativeReferenceName\":\"HTML KPI Variacao Resultado\"}]},\"hasDefaultSort\":true,\"objects\":{}}}",
          "filters": "[]",
          "height": 118.0,
          "width": 239.0,
          "x": 530.0,
          "y": 116.0,
          "z": 1002.0
        },
        {
          "config": "{\"name\":\"v18a717336e0044c184c\",\"layouts\":[{\"id\":0,\"position\":{\"x\":783,\"y\":116,\"z\":1003,\"width\":239,\"height\":118,\"tabOrder\":1003}}],\"singleVisual\":{\"visualType\":\"htmlContent443BE3AD55E043BF878BED274D3A6865\",\"drillFilterOtherVisuals\":true,\"projections\":{\"content\":[{\"queryRef\":\"medidas.HTML KPI Margem\"}]},\"prototypeQuery\":{\"Version\":2,\"From\":[{\"Name\":\"m\",\"Entity\":\"medidas\",\"Type\":0}],\"Select\":[{\"Measure\":{\"Expression\":{\"SourceRef\":{\"Source\":\"m\"}},\"Property\":\"HTML KPI Margem\"},\"Name\":\"medidas.HTML KPI Margem\",\"NativeReferenceName\":\"HTML KPI Margem\"}]},\"hasDefaultSort\":true,\"objects\":{}}}",
          "filters": "[]",
          "height": 118.0,
          "width": 239.0,
          "x": 783.0,
          "y": 116.0,
          "z": 1003.0
        },
        {
          "config": "{\"name\":\"v567ed6e914a34497899\",\"layouts\":[{\"id\":0,\"position\":{\"x\":24,\"y\":256,\"z\":2000,\"width\":470,\"height\":218,\"tabOrder\":2000}}],\"singleVisual\":{\"visualType\":\"lineChart\",\"drillFilterOtherVisuals\":true,\"projections\":{\"Category\":[{\"queryRef\":\"dim_calendario.Ano Mes\",\"active\":true}],\"Y\":[{\"queryRef\":\"medidas.Receita Total\"},{\"queryRef\":\"medidas.Despesa Total\"}],\"Tooltips\":[{\"queryRef\":\"medidas.Receita Total\"},{\"queryRef\":\"medidas.Despesa Total\"},{\"queryRef\":\"medidas.Resultado\"},{\"queryRef\":\"medidas.Margem de Resultado %\"}]},\"prototypeQuery\":{\"Version\":2,\"From\":[{\"Name\":\"d\",\"Entity\":\"dim_calendario\",\"Type\":0},{\"Name\":\"m\",\"Entity\":\"medidas\",\"Type\":0}],\"Select\":[{\"Column\":{\"Expression\":{\"SourceRef\":{\"Source\":\"d\"}},\"Property\":\"Ano Mes\"},\"Name\":\"dim_calendario.Ano Mes\",\"NativeReferenceName\":\"Ano Mes\"},{\"Measure\":{\"Expression\":{\"SourceRef\":{\"Source\":\"m\"}},\"Property\":\"Receita Total\"},\"Name\":\"medidas.Receita Total\",\"NativeReferenceName\":\"Receita Total\"},{\"Measure\":{\"Expression\":{\"SourceRef\":{\"Source\":\"m\"}},\"Property\":\"Despesa Total\"},\"Name\":\"medidas.Despesa Total\",\"NativeReferenceName\":\"Despesa Total\"},{\"Measure\":{\"Expression\":{\"SourceRef\":{\"Source\":\"m\"}},\"Property\":\"Resultado\"},\"Name\":\"medidas.Resultado\",\"NativeReferenceName\":\"Resultado\"},{\"Measure\":{\"Expression\":{\"SourceRef\":{\"Source\":\"m\"}},\"Property\":\"Margem de Resultado %\"},\"Name\":\"medidas.Margem de Resultado %\",\"NativeReferenceName\":\"Margem de Resultado %\"}],\"OrderBy\":[{\"Direction\":1,\"Expression\":{\"Column\":{\"Expression\":{\"SourceRef\":{\"Source\":\"d\"}},\"Property\":\"Ano Mes\"}}}]},\"hasDefaultSort\":true,\"objects\":{\"title\":[{\"properties\":{\"text\":{\"expr\":{\"Literal\":{\"Value\":\"'Receita vs despesa'\"}}}}}]}}}",
          "filters": "[]",
          "height": 218.0,
          "width": 470.0,
          "x": 24.0,
          "y": 256.0,
          "z": 2000.0
        },
        {
          "config": "{\"name\":\"v319586f3c81a4a8e92c\",\"layouts\":[{\"id\":0,\"position\":{\"x\":514,\"y\":256,\"z\":2001,\"width\":490,\"height\":218,\"tabOrder\":2001}}],\"singleVisual\":{\"visualType\":\"waterfallChart\",\"drillFilterOtherVisuals\":true,\"projections\":{\"Category\":[{\"queryRef\":\"dim_calendario.Ano Mes\",\"active\":true}],\"Y\":[{\"queryRef\":\"medidas.Resultado\"}],\"Tooltips\":[{\"queryRef\":\"medidas.Receita Total\"},{\"queryRef\":\"medidas.Despesa Total\"},{\"queryRef\":\"medidas.Resultado\"},{\"queryRef\":\"medidas.Margem de Resultado %\"}]},\"prototypeQuery\":{\"Version\":2,\"From\":[{\"Name\":\"d\",\"Entity\":\"dim_calendario\",\"Type\":0},{\"Name\":\"m\",\"Entity\":\"medidas\",\"Type\":0}],\"Select\":[{\"Column\":{\"Expression\":{\"SourceRef\":{\"Source\":\"d\"}},\"Property\":\"Ano Mes\"},\"Name\":\"dim_calendario.Ano Mes\",\"NativeReferenceName\":\"Ano Mes\"},{\"Measure\":{\"Expression\":{\"SourceRef\":{\"Source\":\"m\"}},\"Property\":\"Resultado\"},\"Name\":\"medidas.Resultado\",\"NativeReferenceName\":\"Resultado\"},{\"Measure\":{\"Expression\":{\"SourceRef\":{\"Source\":\"m\"}},\"Property\":\"Receita Total\"},\"Name\":\"medidas.Receita Total\",\"NativeReferenceName\":\"Receita Total\"},{\"Measure\":{\"Expression\":{\"SourceRef\":{\"Source\":\"m\"}},\"Property\":\"Despesa Total\"},\"Name\":\"medidas.Despesa Total\",\"NativeReferenceName\":\"Despesa Total\"},{\"Measure\":{\"Expression\":{\"SourceRef\":{\"Source\":\"m\"}},\"Property\":\"Margem de Resultado %\"},\"Name\":\"medidas.Margem de Resultado %\",\"NativeReferenceName\":\"Margem de Resultado %\"}],\"OrderBy\":[{\"Direction\":1,\"Expression\":{\"Column\":{\"Expression\":{\"SourceRef\":{\"Source\":\"d\"}},\"Property\":\"Ano Mes\"}}}]},\"hasDefaultSort\":true,\"objects\":{\"title\":[{\"properties\":{\"text\":{\"expr\":{\"Literal\":{\"Value\":\"'Resultado por mes'\"}}}}}]}}}",
          "filters": "[]",
          "height": 218.0,
          "width": 490.0,
          "x": 514.0,
          "y": 256.0,
          "z": 2001.0
        },
        {
          "config": "{\"name\":\"vb6389944ae284dcc9ef\",\"layouts\":[{\"id\":0,\"position\":{\"x\":24,\"y\":498,\"z\":3000,\"width\":470,\"height\":198,\"tabOrder\":3000}}],\"singleVisual\":{\"visualType\":\"lineChart\",\"drillFilterOtherVisuals\":true,\"projections\":{\"Category\":[{\"queryRef\":\"dim_calendario.Ano Mes\",\"active\":true}],\"Y\":[{\"queryRef\":\"medidas.Resultado Acumulado\"}],\"Tooltips\":[{\"queryRef\":\"medidas.Receita Total\"},{\"queryRef\":\"medidas.Despesa Total\"},{\"queryRef\":\"medidas.Resultado\"},{\"queryRef\":\"medidas.Margem de Resultado %\"}]},\"prototypeQuery\":{\"Version\":2,\"From\":[{\"Name\":\"d\",\"Entity\":\"dim_calendario\",\"Type\":0},{\"Name\":\"m\",\"Entity\":\"medidas\",\"Type\":0}],\"Select\":[{\"Column\":{\"Expression\":{\"SourceRef\":{\"Source\":\"d\"}},\"Property\":\"Ano Mes\"},\"Name\":\"dim_calendario.Ano Mes\",\"NativeReferenceName\":\"Ano Mes\"},{\"Measure\":{\"Expression\":{\"SourceRef\":{\"Source\":\"m\"}},\"Property\":\"Resultado Acumulado\"},\"Name\":\"medidas.Resultado Acumulado\",\"NativeReferenceName\":\"Resultado Acumulado\"},{\"Measure\":{\"Expression\":{\"SourceRef\":{\"Source\":\"m\"}},\"Property\":\"Receita Total\"},\"Name\":\"medidas.Receita Total\",\"NativeReferenceName\":\"Receita Total\"},{\"Measure\":{\"Expression\":{\"SourceRef\":{\"Source\":\"m\"}},\"Property\":\"Despesa Total\"},\"Name\":\"medidas.Despesa Total\",\"NativeReferenceName\":\"Despesa Total\"},{\"Measure\":{\"Expression\":{\"SourceRef\":{\"Source\":\"m\"}},\"Property\":\"Resultado\"},\"Name\":\"medidas.Resultado\",\"NativeReferenceName\":\"Resultado\"},{\"Measure\":{\"Expression\":{\"SourceRef\":{\"Source\":\"m\"}},\"Property\":\"Margem de Resultado %\"},\"Name\":\"medidas.Margem de Resultado %\",\"NativeReferenceName\":\"Margem de Resultado %\"}],\"OrderBy\":[{\"Direction\":1,\"Expression\":{\"Column\":{\"Expression\":{\"SourceRef\":{\"Source\":\"d\"}},\"Property\":\"Ano Mes\"}}}]},\"hasDefaultSort\":true,\"objects\":{\"title\":[{\"properties\":{\"text\":{\"expr\":{\"Literal\":{\"Value\":\"'Resultado acumulado'\"}}}}}]}}}",
          "filters": "[]",
          "height": 198.0,
          "width": 470.0,
          "x": 24.0,
          "y": 498.0,
          "z": 3000.0
        },
        {
          "config": "{\"name\":\"v0b58fd7693da4f01882\",\"layouts\":[{\"id\":0,\"position\":{\"x\":514,\"y\":498,\"z\":3001,\"width\":490,\"height\":198,\"tabOrder\":3001}}],\"singleVisual\":{\"visualType\":\"lineChart\",\"drillFilterOtherVisuals\":true,\"projections\":{\"Category\":[{\"queryRef\":\"dim_calendario.Ano Mes\",\"active\":true}],\"Y\":[{\"queryRef\":\"medidas.Margem de Resultado %\"}],\"Tooltips\":[{\"queryRef\":\"medidas.Receita Total\"},{\"queryRef\":\"medidas.Despesa Total\"},{\"queryRef\":\"medidas.Resultado\"},{\"queryRef\":\"medidas.Margem de Resultado %\"}]},\"prototypeQuery\":{\"Version\":2,\"From\":[{\"Name\":\"d\",\"Entity\":\"dim_calendario\",\"Type\":0},{\"Name\":\"m\",\"Entity\":\"medidas\",\"Type\":0}],\"Select\":[{\"Column\":{\"Expression\":{\"SourceRef\":{\"Source\":\"d\"}},\"Property\":\"Ano Mes\"},\"Name\":\"dim_calendario.Ano Mes\",\"NativeReferenceName\":\"Ano Mes\"},{\"Measure\":{\"Expression\":{\"SourceRef\":{\"Source\":\"m\"}},\"Property\":\"Margem de Resultado %\"},\"Name\":\"medidas.Margem de Resultado %\",\"NativeReferenceName\":\"Margem de Resultado %\"},{\"Measure\":{\"Expression\":{\"SourceRef\":{\"Source\":\"m\"}},\"Property\":\"Receita Total\"},\"Name\":\"medidas.Receita Total\",\"NativeReferenceName\":\"Receita Total\"},{\"Measure\":{\"Expression\":{\"SourceRef\":{\"Source\":\"m\"}},\"Property\":\"Despesa Total\"},\"Name\":\"medidas.Despesa Total\",\"NativeReferenceName\":\"Despesa Total\"},{\"Measure\":{\"Expression\":{\"SourceRef\":{\"Source\":\"m\"}},\"Property\":\"Resultado\"},\"Name\":\"medidas.Resultado\",\"NativeReferenceName\":\"Resultado\"}],\"OrderBy\":[{\"Direction\":1,\"Expression\":{\"Column\":{\"Expression\":{\"SourceRef\":{\"Source\":\"d\"}},\"Property\":\"Ano Mes\"}}}]},\"hasDefaultSort\":true,\"objects\":{\"title\":[{\"properties\":{\"text\":{\"expr\":{\"Literal\":{\"Value\":\"'Margem por mes'\"}}}}}]}}}",
          "filters": "[]",
          "height": 198.0,
          "width": 490.0,
          "x": 514.0,
          "y": 498.0,
          "z": 3001.0
        }
      ],
      "width": 1280.0
    },
    {
      "config": "{}",
      "displayName": "Detalhamento",
      "displayOption": 1,
      "filters": "[]",
      "height": 720.0,
      "name": "sec_detalhamento",
      "ordinal": 4,
      "visualContainers": [
        {
          "config": "{\"name\":\"v14ccd365424f4136ba7\",\"layouts\":[{\"id\":0,\"position\":{\"x\":24,\"y\":20,\"z\":100,\"width\":540,\"height\":78,\"tabOrder\":100}}],\"singleVisual\":{\"visualType\":\"htmlContent443BE3AD55E043BF878BED274D3A6865\",\"drillFilterOtherVisuals\":true,\"projections\":{\"content\":[{\"queryRef\":\"medidas.HTML Header Detalhamento\"}]},\"prototypeQuery\":{\"Version\":2,\"From\":[{\"Name\":\"m\",\"Entity\":\"medidas\",\"Type\":0}],\"Select\":[{\"Measure\":{\"Expression\":{\"SourceRef\":{\"Source\":\"m\"}},\"Property\":\"HTML Header Detalhamento\"},\"Name\":\"medidas.HTML Header Detalhamento\",\"NativeReferenceName\":\"HTML Header Detalhamento\"}]},\"hasDefaultSort\":true,\"objects\":{}}}",
          "filters": "[]",
          "height": 78.0,
          "width": 540.0,
          "x": 24.0,
          "y": 20.0,
          "z": 100.0
        },
        {
          "config": "{\"name\":\"vc3ce27f6e10241bf803\",\"layouts\":[{\"id\":0,\"position\":{\"x\":584,\"y\":37,\"z\":150,\"width\":420,\"height\":36,\"tabOrder\":150}}],\"singleVisual\":{\"visualType\":\"pageNavigator\",\"drillFilterOtherVisuals\":true}}",
          "filters": "[]",
          "height": 36.0,
          "width": 420.0,
          "x": 584.0,
          "y": 37.0,
          "z": 150.0
        },
        {
          "config": "{\"name\":\"v5b086d3cb9a14bcca7b\",\"layouts\":[{\"id\":0,\"position\":{\"x\":1024,\"y\":20,\"z\":50,\"width\":232,\"height\":676,\"tabOrder\":50}}],\"singleVisual\":{\"visualType\":\"htmlContent443BE3AD55E043BF878BED274D3A6865\",\"drillFilterOtherVisuals\":true,\"projections\":{\"content\":[{\"queryRef\":\"medidas.HTML Filter Panel\"}]},\"prototypeQuery\":{\"Version\":2,\"From\":[{\"Name\":\"m\",\"Entity\":\"medidas\",\"Type\":0}],\"Select\":[{\"Measure\":{\"Expression\":{\"SourceRef\":{\"Source\":\"m\"}},\"Property\":\"HTML Filter Panel\"},\"Name\":\"medidas.HTML Filter Panel\",\"NativeReferenceName\":\"HTML Filter Panel\"}]},\"hasDefaultSort\":true,\"objects\":{}}}",
          "filters": "[]",
          "height": 676.0,
          "width": 232.0,
          "x": 1024.0,
          "y": 20.0,
          "z": 50.0
        },
        {
          "config": "{\"name\":\"v4a71331903124c17b11\",\"layouts\":[{\"id\":0,\"position\":{\"x\":1042,\"y\":164,\"z\":10000,\"width\":196,\"height\":58,\"tabOrder\":10000}}],\"singleVisual\":{\"visualType\":\"slicer\",\"drillFilterOtherVisuals\":true,\"projections\":{\"Values\":[{\"queryRef\":\"dim_calendario.Ano\",\"active\":true}]},\"prototypeQuery\":{\"Version\":2,\"From\":[{\"Name\":\"d\",\"Entity\":\"dim_calendario\",\"Type\":0}],\"Select\":[{\"Column\":{\"Expression\":{\"SourceRef\":{\"Source\":\"d\"}},\"Property\":\"Ano\"},\"Name\":\"dim_calendario.Ano\",\"NativeReferenceName\":\"Ano\"}]},\"hasDefaultSort\":true,\"objects\":{\"title\":[{\"properties\":{\"text\":{\"expr\":{\"Literal\":{\"Value\":\"'Ano'\"}}}}}]}}}",
          "filters": "[]",
          "height": 58.0,
          "width": 196.0,
          "x": 1042.0,
          "y": 164.0,
          "z": 10000.0
        },
        {
          "config": "{\"name\":\"vb4efff758aaf43ba9c5\",\"layouts\":[{\"id\":0,\"position\":{\"x\":1042,\"y\":234,\"z\":10001,\"width\":196,\"height\":58,\"tabOrder\":10001}}],\"singleVisual\":{\"visualType\":\"slicer\",\"drillFilterOtherVisuals\":true,\"projections\":{\"Values\":[{\"queryRef\":\"dim_calendario.Mes Nome\",\"active\":true}]},\"prototypeQuery\":{\"Version\":2,\"From\":[{\"Name\":\"d\",\"Entity\":\"dim_calendario\",\"Type\":0}],\"Select\":[{\"Column\":{\"Expression\":{\"SourceRef\":{\"Source\":\"d\"}},\"Property\":\"Mes Nome\"},\"Name\":\"dim_calendario.Mes Nome\",\"NativeReferenceName\":\"Mes Nome\"}]},\"hasDefaultSort\":true,\"objects\":{\"title\":[{\"properties\":{\"text\":{\"expr\":{\"Literal\":{\"Value\":\"'Mes'\"}}}}}]}}}",
          "filters": "[]",
          "height": 58.0,
          "width": 196.0,
          "x": 1042.0,
          "y": 234.0,
          "z": 10001.0
        },
        {
          "config": "{\"name\":\"vf9088e21060d44a2a51\",\"layouts\":[{\"id\":0,\"position\":{\"x\":1042,\"y\":304,\"z\":10002,\"width\":196,\"height\":58,\"tabOrder\":10002}}],\"singleVisual\":{\"visualType\":\"slicer\",\"drillFilterOtherVisuals\":true,\"projections\":{\"Values\":[{\"queryRef\":\"dim_categoria.nome_categoria\",\"active\":true}]},\"prototypeQuery\":{\"Version\":2,\"From\":[{\"Name\":\"c\",\"Entity\":\"dim_categoria\",\"Type\":0}],\"Select\":[{\"Column\":{\"Expression\":{\"SourceRef\":{\"Source\":\"c\"}},\"Property\":\"nome_categoria\"},\"Name\":\"dim_categoria.nome_categoria\",\"NativeReferenceName\":\"nome_categoria\"}]},\"hasDefaultSort\":true,\"objects\":{\"title\":[{\"properties\":{\"text\":{\"expr\":{\"Literal\":{\"Value\":\"'Categoria'\"}}}}}]}}}",
          "filters": "[]",
          "height": 58.0,
          "width": 196.0,
          "x": 1042.0,
          "y": 304.0,
          "z": 10002.0
        },
        {
          "config": "{\"name\":\"v12622a5e3c7e4acda16\",\"layouts\":[{\"id\":0,\"position\":{\"x\":1042,\"y\":374,\"z\":10003,\"width\":196,\"height\":58,\"tabOrder\":10003}}],\"singleVisual\":{\"visualType\":\"slicer\",\"drillFilterOtherVisuals\":true,\"projections\":{\"Values\":[{\"queryRef\":\"dim_forma_pagamento.forma\",\"active\":true}]},\"prototypeQuery\":{\"Version\":2,\"From\":[{\"Name\":\"p\",\"Entity\":\"dim_forma_pagamento\",\"Type\":0}],\"Select\":[{\"Column\":{\"Expression\":{\"SourceRef\":{\"Source\":\"p\"}},\"Property\":\"forma\"},\"Name\":\"dim_forma_pagamento.forma\",\"NativeReferenceName\":\"forma\"}]},\"hasDefaultSort\":true,\"objects\":{\"title\":[{\"properties\":{\"text\":{\"expr\":{\"Literal\":{\"Value\":\"'Forma'\"}}}}}]}}}",
          "filters": "[]",
          "height": 58.0,
          "width": 196.0,
          "x": 1042.0,
          "y": 374.0,
          "z": 10003.0
        },
        {
          "config": "{\"name\":\"v7988b0a128cb4017869\",\"layouts\":[{\"id\":0,\"position\":{\"x\":1042,\"y\":444,\"z\":10004,\"width\":196,\"height\":58,\"tabOrder\":10004}}],\"singleVisual\":{\"visualType\":\"slicer\",\"drillFilterOtherVisuals\":true,\"projections\":{\"Values\":[{\"queryRef\":\"fat_lancamentos_financeiros.tipo\",\"active\":true}]},\"prototypeQuery\":{\"Version\":2,\"From\":[{\"Name\":\"f\",\"Entity\":\"fat_lancamentos_financeiros\",\"Type\":0}],\"Select\":[{\"Column\":{\"Expression\":{\"SourceRef\":{\"Source\":\"f\"}},\"Property\":\"tipo\"},\"Name\":\"fat_lancamentos_financeiros.tipo\",\"NativeReferenceName\":\"tipo\"}]},\"hasDefaultSort\":true,\"objects\":{\"title\":[{\"properties\":{\"text\":{\"expr\":{\"Literal\":{\"Value\":\"'Tipo'\"}}}}}]}}}",
          "filters": "[]",
          "height": 58.0,
          "width": 196.0,
          "x": 1042.0,
          "y": 444.0,
          "z": 10004.0
        },
        {
          "config": "{\"name\":\"va82308cb557a4e2f8ad\",\"layouts\":[{\"id\":0,\"position\":{\"x\":1042,\"y\":514,\"z\":10005,\"width\":196,\"height\":78,\"tabOrder\":10005}}],\"singleVisual\":{\"visualType\":\"slicer\",\"drillFilterOtherVisuals\":true,\"projections\":{\"Values\":[{\"queryRef\":\"fat_lancamentos_financeiros.descricao\",\"active\":true}]},\"prototypeQuery\":{\"Version\":2,\"From\":[{\"Name\":\"f\",\"Entity\":\"fat_lancamentos_financeiros\",\"Type\":0}],\"Select\":[{\"Column\":{\"Expression\":{\"SourceRef\":{\"Source\":\"f\"}},\"Property\":\"descricao\"},\"Name\":\"fat_lancamentos_financeiros.descricao\",\"NativeReferenceName\":\"descricao\"}]},\"hasDefaultSort\":true,\"objects\":{\"title\":[{\"properties\":{\"text\":{\"expr\":{\"Literal\":{\"Value\":\"'Busca'\"}}}}}]}}}",
          "filters": "[]",
          "height": 78.0,
          "width": 196.0,
          "x": 1042.0,
          "y": 514.0,
          "z": 10005.0
        },
        {
          "config": "{\"name\":\"v9c096214119e499db35\",\"layouts\":[{\"id\":0,\"position\":{\"x\":24,\"y\":126,\"z\":2000,\"width\":980,\"height\":570,\"tabOrder\":2000}}],\"singleVisual\":{\"visualType\":\"tableEx\",\"drillFilterOtherVisuals\":true,\"projections\":{\"Values\":[{\"queryRef\":\"fat_lancamentos_financeiros.id\"},{\"queryRef\":\"fat_lancamentos_financeiros.data_lancamento\"},{\"queryRef\":\"fat_lancamentos_financeiros.tipo\"},{\"queryRef\":\"fat_lancamentos_financeiros.descricao\"},{\"queryRef\":\"dim_categoria.nome_categoria\",\"active\":true},{\"queryRef\":\"dim_forma_pagamento.forma\",\"active\":true},{\"queryRef\":\"fat_lancamentos_financeiros.valor\"},{\"queryRef\":\"fat_lancamentos_financeiros.observacao\"},{\"queryRef\":\"fat_lancamentos_financeiros.criado_em\"}]},\"prototypeQuery\":{\"Version\":2,\"From\":[{\"Name\":\"f\",\"Entity\":\"fat_lancamentos_financeiros\",\"Type\":0},{\"Name\":\"c\",\"Entity\":\"dim_categoria\",\"Type\":0},{\"Name\":\"p\",\"Entity\":\"dim_forma_pagamento\",\"Type\":0}],\"Select\":[{\"Column\":{\"Expression\":{\"SourceRef\":{\"Source\":\"f\"}},\"Property\":\"id\"},\"Name\":\"fat_lancamentos_financeiros.id\",\"NativeReferenceName\":\"id\"},{\"Column\":{\"Expression\":{\"SourceRef\":{\"Source\":\"f\"}},\"Property\":\"data_lancamento\"},\"Name\":\"fat_lancamentos_financeiros.data_lancamento\",\"NativeReferenceName\":\"data_lancamento\"},{\"Column\":{\"Expression\":{\"SourceRef\":{\"Source\":\"f\"}},\"Property\":\"tipo\"},\"Name\":\"fat_lancamentos_financeiros.tipo\",\"NativeReferenceName\":\"tipo\"},{\"Column\":{\"Expression\":{\"SourceRef\":{\"Source\":\"f\"}},\"Property\":\"descricao\"},\"Name\":\"fat_lancamentos_financeiros.descricao\",\"NativeReferenceName\":\"descricao\"},{\"Column\":{\"Expression\":{\"SourceRef\":{\"Source\":\"c\"}},\"Property\":\"nome_categoria\"},\"Name\":\"dim_categoria.nome_categoria\",\"NativeReferenceName\":\"nome_categoria\"},{\"Column\":{\"Expression\":{\"SourceRef\":{\"Source\":\"p\"}},\"Property\":\"forma\"},\"Name\":\"dim_forma_pagamento.forma\",\"NativeReferenceName\":\"forma\"},{\"Column\":{\"Expression\":{\"SourceRef\":{\"Source\":\"f\"}},\"Property\":\"valor\"},\"Name\":\"fat_lancamentos_financeiros.valor\",\"NativeReferenceName\":\"valor\"},{\"Column\":{\"Expression\":{\"SourceRef\":{\"Source\":\"f\"}},\"Property\":\"observacao\"},\"Name\":\"fat_lancamentos_financeiros.observacao\",\"NativeReferenceName\":\"observacao\"},{\"Column\":{\"Expression\":{\"SourceRef\":{\"Source\":\"f\"}},\"Property\":\"criado_em\"},\"Name\":\"fat_lancamentos_financeiros.criado_em\",\"NativeReferenceName\":\"criado_em\"}],\"OrderBy\":[{\"Direction\":2,\"Expression\":{\"Column\":{\"Expression\":{\"SourceRef\":{\"Source\":\"f\"}},\"Property\":\"data_lancamento\"}}}]},\"hasDefaultSort\":true,\"objects\":{\"title\":[{\"properties\":{\"text\":{\"expr\":{\"Literal\":{\"Value\":\"'Lancamentos financeiros'\"}}}}}]}}}",
          "filters": "[]",
          "height": 570.0,
          "width": 980.0,
          "x": 24.0,
          "y": 126.0,
          "z": 2000.0
        }
      ],
      "width": 1280.0
    }
  ]
}
